Workbook

Sheet アイデア集
A1: テーマ | B1: テーマ名 | C1: 一言で | D1: 代表例 | E1: 標準機能との違い | F1: 独自アプローチのヒント（抜粋） | G1: 自作の難しさ | H1: 関連LISP（件） | I1: 詳しい解説
A2: T01 | B2: 操作に反応して自動処理（リアクター） | C2: コマンドや保存を見張り、決まった処理を自動実行 | D2: Layer Director（英語圏）、LATT（ヨーロッパ）、Automatic Block Break（英語圏）、LISP Ánh xạ giá trị đối tượng（ベトナム・東南アジア）、修正文字自動赤化（日本） | E2: 標準は一部図形の画層固定のみ。任意の操作に割り込む仕組みはない | F2: 保存時に社内規定違反（画層名・色）を見つけて一覧で警告する見張り番 | G2: ★★★ | H2: 40 | I2: catalog/アイデア集/T01_操作に反応して自動処理（リアクター）.md
A3: T02 | B3: 図面を開かずに一括処理 | C3: 多数の図面を開かずに裏で調べたり書き換えたりする | D3: 批量制作目录—不开图提取块属性（中国語圏）、DBXscanBlocks（英語圏）、ODBX_LIB（ヨーロッパ）、cpdf.lsp（ベトナム・東南アジア）、ObjectDBX Wrapper（英語圏） | E3: 標準は覗く・抽出する程度。開かずに一括で書き換える機能はない | F3: 図枠属性とファイル名・更新日を並べた図面台帳を自動作成し食い違いに印を付ける | G3: ★★★ | H3: 53 | I3: catalog/アイデア集/T02_図面を開かずに一括処理.md
A4: T03 | B4: 複数図面へのスクリプト一括実行 | C4: フォルダ内の図面に同じ作業や自作LISPを自動で繰り返す | D4: CAD Batch Runner（英語圏）、Batch Find & Replace Text（英語圏）、Batch DWG-Commander（日本）、SCRIPTOR（ヨーロッパ）、块更新（中国語圏） | E4: SCRIPTはあるが複数図面用の手順は自作。LISPを選んで全図面に適用する画面はない | F4: 処理前後の変化数と警告を図面ごとに表にし、確認すべき図面だけを示す | G4: ★★ | H4: 75 | I4: catalog/アイデア集/T03_複数図面へのスクリプト一括実行.md
A5: T04 | B5: 図枠の自動認識→一括印刷 | C5: モデル空間の図枠を自動で見つけて一括印刷・PDF化 | D5: 批量打印-邱枫版（中国語圏）、PlotDWGarr ほか（英語圏）、FrameFinder（ロシア語圏）、ABP-Batch Plot（ベトナム・東南アジア）、export_dwf_main（GitHub） | E5: 標準はレイアウト単位の一括印刷のみ。モデル内の図枠検出や用紙自動判定はない | F5: 図枠の図番属性を読み取りPDFファイル名を「図番_図名」にして一括出力 | G5: ★★ | H5: 139 | I5: catalog/アイデア集/T04_図枠の自動認識→一括印刷.md
A6: T05 | B6: 図枠からレイアウト・ビューポートを自動作成 | C6: 図枠1つごとにレイアウトとビューポートを自動作成 | D6: Auto layout LISP（英語圏）、AUTOLAMINAS（その他の地域）、FrameFinder（ロシア語圏）、Ghép khung bản đồ（ベトナム・東南アジア）、VPTOMODEL（日本） | E6: 標準は手作業で1枚ずつ作成。図枠からの量産や図番によるレイアウト名付けはない | F6: 図枠を動かし増やしても既存レイアウトを消さず差分だけ更新する | G6: ★★ | H6: 175 | I6: catalog/アイデア集/T05_図枠からレイアウト・ビューポートを自動作成.md
A7: T06 | B7: 図枠の属性を自動更新 | C7: 図枠の図番・日付・頁番号を自動記入し目録も作る | D7: RenameLOA reactor（英語圏）、@lisp工程管理（中国語圏）、Update Titleblock Attributes（英語圏）、Tạo Danh mục bản vẽ tự động（ベトナム・東南アジア）、NUMERAR_PLANOS（その他の地域） | E7: 標準は属性の個別編集とフィールド程度。Excelからの一括流し込みや規則的な再採番はない | F7: 図面目録のExcelを元データにして図枠へ流し込み、図面側の変更は色付きで書き戻す | G7: ★★ | H7: 89 | I7: catalog/アイデア集/T06_図枠の属性を自動更新.md
A8: T07 | B8: 検図：寸法値の手入力上書きを検出 | C8: 手で書き換えた寸法値を見つけて色で知らせる | D8: DIMPOLICE（日本）、OverDimCol（英語圏）、DIMLFAC可視化（ロシア語圏）、FakeDims（ベトナム・東南アジア）、尺寸原值（中国語圏） | E8: 標準はプロパティで1件ずつ確認のみ。自動の色付け・実測値との差の表示は無い | F8: 書かれた値と実測値の差の大きさで3段階に色分けし、直す優先順位を見せる | G8: ★ | H8: 53 | I8: catalog/アイデア集/T07_検図：寸法値の手入力上書きを検出.md
A9: T08 | B9: 検図：わずかなずれ・隙間・重なりを検出 | C9: 見えない小さな隙間・傾き・重なりを探して印を付ける | D9: ZureMikke（日本）、TxtOverlap（英語圏）、Gaps（英語圏）、定位压线字（中国語圏）、EL-CHECK（ロシア語圏） | E9: 標準はOVERKILL・JOINで直すのみ。隙間や傾きの場所を見つけて示す機能は無い | F9: 隙間・傾き・重なり・開いた線を色分けし、1回で検図レポート化。許容値は図面尺度から自動決定 | G9: ★★ | H9: 81 | I9: catalog/アイデア集/T08_検図：わずかなずれ・隙間・重なりを検出.md
A10: T09 | B10: 新旧図面の差分比較・雲マーク | C10: 修正前後を比べ、変わった所に自動で雲マークを付ける | D10: DiffCheck（GitHub）、阿甘对图器（中国語圏）、修正文字自動赤化（日本）、2図面比較ツール（ベトナム・東南アジア）、LogBook（英語圏） | E10: 標準DWGCOMPAREは図面単位の比較。図面内の範囲比較や改訂欄記入は不可 | F10: 追加・削除・移動・文字変更で雲の色を分け、改訂△と改訂欄への記入まで自動化する | G10: ★★★ | H10: 33 | I10: catalog/アイデア集/T09_新旧図面の差分比較・雲マーク.md
A11: T10 | B11: 図面の健全性チェック・お掃除 | C11: 図面にたまったゴミや不具合を調べて一括で掃除する | D11: DrawingHealthScore（GitHub）、CAD批量清理（中国語圏）、DBXremSL（英語圏）、Finalizer（日本）、odbx_purge（ヨーロッパ） | E11: 標準はPURGE・AUDIT等を1図面ずつ。開かずに一括掃除や状態の点数化は無い | F11: 掃除前後のサイズ・画層数などを比べたビフォーアフター表を出し、効果を見える化する | G11: ★★ | H11: 154 | I11: catalog/アイデア集/T10_図面の健全性チェック・お掃除.md
A12: T11 | B12: 文字の重なりを自動で避ける・整列 | C12: 重なった文字を自動でずらし、きれいに並べる | D12: 文字避让（中国語圏）、MLeaderSmartAlign（GitHub）、TxtOverlap（英語圏）、JustifyTextAuto（日本）、Overlapping texts（ヨーロッパ） | E12: 標準はTEXTALIGN等の整列のみ。重なった文字を見つけて自動で逃がす機能は無い | F12: 文字の種類ごとに優先度を決め、重要な文字は動かさず他を逃がす。印刷時の離れ量で判定 | G12: ★★★ | H12: 136 | I12: catalog/アイデア集/T11_文字の重なりを自動で避ける・整列.md
A13: T12 | B13: 文字の一括検索・置換 | C13: 複数図面や大量の文字をルールに沿って一括で書き換える | D13: Batch Find & Replace Text（英語圏）、図面対訳翻訳LISP（ベトナム・東南アジア）、QE剪贴板批量替换（中国語圏）、odbx_subst（ヨーロッパ）、交点へクリップボード一括貼付（日本） | E13: 標準FINDは開いた図面のみ。複数図面・正規表現・Excel表による置換は不可 | F13: 全角半角・㎜とmm・長音記号など日本語の表記ゆれを一括で統一するモードを作る | G13: ★★ | H13: 509 | I13: catalog/アイデア集/T12_文字の一括検索・置換.md
... A31: T30 | B31: AI・OCR・翻訳など新技術との連携 | C31: AI・OCR・翻訳・地図サービスをAutoCADから呼び出す | D31: Lisp dịch thuật bản vẽ song ngữ（ベトナム・東南アジア）、PDFOCRTEXT（中国語圏）、AIGC（中国語圏）、JSONout/JSONin（英語圏）、拡張エンティティ属性付与（日本） | E31: 標準はPDF取込とSHX文字認識程度で、一括翻訳・任意AIでの図面チェックは不可 | F31: 図面文字・寸法をJSON化してAIに表記ゆれや寸法の食い違いをチェックさせる | G31: ★★★ | H31: 103 | I31: catalog/アイデア集/T30_AI・OCR・翻訳など新技術との連携.md
A33: 使い方：「総合一覧」シートの「テーマ」列で T15 などと絞り込むと、そのテーマの関連LISPがすべて表示されます（ダウンロード対象の選定に使えます）。

Sheet 総合一覧
A1: 順位 | B1: 地域 | C1: 分野 | D1: テーマ | E1: テーマ名 | F1: コマンド | G1: 名前 | H1: 何をするツールか | I1: 非代替性 | J1: 斬新さ | K1: 時短効果 | L1: 汎用性 | M1: 合計 | N1: 評価メモ | O1: 作者 | P1: サイト | Q1: リンク | R1: 入手方法（見込み） | S1: 形式（見込み） | T1: 同じツールの別掲載 | U1: ID
A2: =RANK(M2,$M$2:$M$6943) | B2: 英語圏 | C2: 画層 | D2: T18,T01 | E2: 画層の自動振り分け・標準化、操作に反応して自動処理（リアクター） | F2: LDON / LDOFF | G2: Layer Director | H2: コマンド毎に画層を自動切替 | I2: 21 | J2: 23 | K2: 17 | L2: 20 | M2: =SUM(I2:L2) | N2: コマンド毎に画層自動切替 | O2: Lee Mac | P2: Lee Mac Programming | Q2: 開く | R2: 配布ページからダウンロード | S2: ソース | U2: W1
A3: =RANK(M3,$M$2:$M$6943) | B3: GitHub | C3: 外部参照・図面管理・一括処理 | D3: T09 | E3: 新旧図面の差分比較・雲マーク | F3: DFC / DiffCheck | G3: DiffCheck | H3: 新旧範囲を自動位置合わせし変更箇所に雲マーク | I3: 24 | J3: 22 | K3: 18 | L3: 16 | M3: =SUM(I3:L3) | N3: 新旧差分に自動雲マーク | O3: beastt1992 | P3: GitHub: beastt1992/DiffCheck | Q3: 開く | R3: GitHub（一括取得可） | S3: ソース | U3: W2
A4: =RANK(M4,$M$2:$M$6943) | B4: 中国語圏 | C4: 外部参照・図面管理・一括処理 | D4: T28 | E4: 作業環境の保存・復元 | F4: 上班/下班 | G4: 会话管理 (@lisp会话) | H4: 開いている図面群を保存し翌日一括再開 | I4: 22 | J4: 20 | K4: 17 | L4: 21 | M4: =SUM(I4:L4) | N4: 作業セッション保存が秀逸 | O4: VitalGG | P4: @lisp 应用云 | Q4: 開く | R4: 配布ページからダウンロード | S4: ソース（GitHubにも公開） | U4: W3
A5: =RANK(M5,$M$2:$M$6943) | B5: 中国語圏 | C5: 印刷・レイアウト・図枠 | D5: T04 | E5: 図枠の自動認識→一括印刷 | F5: 批量打印 | G5: 批量打印-邱枫版 (Batchplot) | H5: 1図面多図枠を自動判定し一括印刷・分図 | I5: 20 | J5: 15 | K5: 23 | L5: 22 | M5: =SUM(I5:L5) | N5: 中国で最も普及した一括印刷 | O5: 邱枫 | P5: @lisp 应用云 | Q5: 開く | R5: 配布ページからダウンロード | S5: ソース（GitHubにも公開） | U5: W4
A6: =RANK(M6,$M$2:$M$6943) | B6: 中国語圏 | C6: 印刷・レイアウト・図枠 | D6: T04 | E6: 図枠の自動認識→一括印刷 | F6: BatchPlot | G6: 批量打印程序v3.6.1 (秋枫版改) | H6: 図枠を自動認識し1図面多図枠を一括印刷 | I6: 20 | J6: 15 | K6: 23 | L6: 22 | M6: =SUM(I6:L6) | N6: 中国標準の一括印刷 | O6: ludaweb/秋枫 | P6: 明经CAD社区 | Q6: 開く | R6: フォーラム添付（ログインが必要な場合あり） | S6: 不明 | U6: W5
A7: =RANK(M7,$M$2:$M$6943) | B7: 中国語圏 | C7: 印刷・レイアウト・図枠 | D7: T04 | E7: 図枠の自動認識→一括印刷 | F7: AI识别图框/批打输出 | G7: 智能识别图框批量打印 (@打印输出) | H7: 図枠をPL/線/ブロックから識別し一括印刷 | I7: 20 | J7: 17 | K7: 22 | L7: 21 | M7: =SUM(I7:L7) | N7: 図枠自動認識の一括印刷 | O7: VitalGG | P7: @lisp 应用云 | Q7: 開く | R7: 配布ページからダウンロード | S7: ソース（GitHubにも公開） | U7: W6
A8: =RANK(M8,$M$2:$M$6943) | B8: GitHub | C8: 外部参照・図面管理・一括処理 | D8: T10 | E8: 図面の健全性チェック・お掃除 | F8: DHS / DHSFIX | G8: DrawingHealthScore | H8: 図面の健全度を100点評価し一括修正 | I8: 22 | J8: 21 | K8: 17 | L8: 18 | M8: =SUM(I8:L8) | N8: 図面健全度スコア化が斬新 | O8: beastt1992 | P8: GitHub: beastt1992/DrawingHealthScore | Q8: 開く | R8: GitHub（一括取得可） | S8: ソース | U8: W7
A9: =RANK(M9,$M$2:$M$6943) | B9: 英語圏 | C9: 画層 | D9: T18,T01 | E9: 画層の自動振り分け・標準化、操作に反応して自動処理（リアクター） | F9: FLAY | G9: FLay | H9: 作図時に指定画層へ自動振分け | I9: 20 | J9: 19 | K9: 18 | L9: 21 | M9: =SUM(I9:L9) | N9: 作図時自動画層振分け | O9: CAD Studio | P9: CAD Forum | Q9: 開く | R9: 配布ページからダウンロード | S9: ソース/暗号化（.vlx）混在 | U9: W8
A10: =RANK(M10,$M$2:$M$6943) | B10: 中国語圏 | C10: 文字・テキスト | D10: T11 | E10: 文字の重なりを自動で避ける・整列 | F10: 文字避让 | G10: 文字避让 (@lisp文本) | H10: 重なった単線文字を自動で逃がし配置 | I10: 22 | J10: 20 | K10: 17 | L10: 18 | M10: =SUM(I10:L10) | N10: 重なり自動回避は独自 | O10: VitalGG | P10: @lisp 应用云 | Q10: 開く | R10: 配布ページからダウンロード | S10: ソース（GitHubにも公開） | U10: W9
A11: =RANK(M11,$M$2:$M$6943) | B11: 英語圏 | C11: 文字・テキスト | D11: T15 | E11: 連番の自動記入 | F11: NumInc | G11: Incremental Numbering Suite | H11: 連番文字・属性を配置 | I11: 18 | J11: 15 | K11: 21 | L11: 22 | M11: =SUM(I11:L11) | N11: 連番配置の決定版、多機能 | O11: Lee Mac | P11: Lee Mac Programming | Q11: 開く | R11: 配布ページからダウンロード | S11: ソース | U11: W10
A12: =RANK(M12,$M$2:$M$6943) | B12: 英語圏 | C12: ハッチ・面積・長さ集計 | D12: T13,T16 | E12: 図形と数値の連動（フィールド・面積表）、数量拾い・集計表 | F12: AOL | G12: Area Object Link (AOL) | H12: 面積・周長を属性にリンクし集計表 | I12: 20 | J12: 19 | K12: 20 | L12: 16 | M12: =SUM(I12:L12) | N12: 面積を属性リンクし集計表 | O12: @The Office | P12: Autodesk App Store | Q12: 開く | R12: アプリストア経由（Autodeskアカウントが必要） | S12: 暗号化・インストーラ | U12: W11
A13: =RANK(M13,$M$2:$M$6943) | B13: 英語圏 | C13: 外部参照・図面管理・一括処理 | D13: T03 | E13: 複数図面へのスクリプト一括実行 | F13: - | G13: CAD Batch Runner | H13: 複数図面にスクリプト/LISPを一括実行 | I13: 18 | J13: 13 | K13: 22 | L13: 22 | M13: =SUM(I13:L13) | N13: 複数図面に一括実行 | O13: ESurveying Softech | P13: eSurveying | Q13: 開く | R13: 配布ページからダウンロード | S13: 暗号化（.fas）が中心 | U13: W12
... A45: =RANK(M45,$M$2:$M$6943) | B45: 英語圏 | C45: 外部参照・図面管理・一括処理 | D45: T14,T03 | E45: 属性の抽出・一括編集・Excelとの往復、複数図面へのスクリプト一括実行 | F45: batte | G45: Batch Attribute Editor | H45: 複数図面の属性を一括編集 | I45: 19 | J45: 13 | K45: 20 | L45: 18 | M45: =SUM(I45:L45) | N45: 図面を開かず属性一括編集 | O45: Lee Mac | P45: Lee Mac Programming | Q45: 開く | R45: 配布ページからダウンロード | S45: ソース | U45: W44
A46: =RANK(M46,$M$2:$M$6943) | B46: 英語圏 | C46: 文字・テキスト | D46: T15 | E46: 連番の自動記入 | F46: NUMINC | G46: Incremental Numbering (NumInc) | H46: 連番テキスト・ブロックを配置 | I46: 16 | J46: 14 | K46: 19 | L46: 21 | M46: =SUM(I46:L46) | N46: 連番文字・ブロック両対応 | O46: MEP WORK | P46: MEP WORK | Q46: 開く | R46: 配布ページからダウンロード | S46: 不明 | T46: MEP Details | U46: W45
A47: =RANK(M47,$M$2:$M$6943) | B47: ベトナム・東南アジア | C47: 文字・テキスト | D47: T30,T12 | E47: AI・OCR・翻訳など新技術との連携、文字の一括検索・置換 | F47: AIT | G47: Lisp dịch thuật bản vẽ song ngữ AutoCAD | H47: AIで図面文字を対訳翻訳（有料） | I47: 21 | J47: 19 | K47: 16 | L47: 14 | M47: =SUM(I47:L47) | N47: AIで図面を対訳翻訳 | O47: AJS / AutoLISP Thật là đơn giản | P47: lisp.vn (AutoLISP Reviewer) | Q47: 開く | R47: 有料 | S47: 不明 | U47: W46
A48: =RANK(M48,$M$2:$M$6943) | B48: 中国語圏 | C48: 作図 | D48: その他 | E48: その他 | F48: S | G48: 填充图案拉伸6.0 | H48: ハッチ境界ごと追従させるSTRETCH代替 | I48: 19 | J48: 16 | K48: 17 | L48: 18 | M48: =SUM(I48:L48) | N48: ハッチも伸びるSTRETCH | O48: 陈伟 | P48: 明经CAD社区 | Q48: 開く | R48: フォーラム添付（ログインが必要な場合あり） | S48: 不明 | U48: W47
A49: =RANK(M49,$M$2:$M$6943) | B49: 中国語圏 | C49: 文字・テキスト | D49: T08,T11 | E49: 検図：わずかなずれ・隙間・重なりを検出、文字の重なりを自動で避ける・整列 | F49: 定位压线字 | G49: 定位压线字 (@lisp文本) | H49: 線と重なっている文字を強調表示 | I49: 21 | J49: 18 | K49: 13 | L49: 18 | M49: =SUM(I49:L49) | N49: 図面チェック用に有用 | O49: VitalGG | P49: @lisp 应用云 | Q49: 開く | R49: 配布ページからダウンロード | S49: ソース（GitHubにも公開） | U49: W48
A50: =RANK(M50,$M$2:$M$6943) | B50: 中国語圏 | C50: 作図 | D50: その他 | E50: その他 | F50: S | G50: 带填充拉伸_v8.6（记忆拉伸） | H50: ハッチ連動ストレッチ・前回値記憶 | I50: 19 | J50: 16 | K50: 17 | L50: 18 | M50: =SUM(I50:L50) | N50: ハッチ連動STRETCH | O50: kucha007 | P50: 明经CAD社区 | Q50: 開く | R50: フォーラム添付（ログインが必要な場合あり） | S50: 不明 | U50: W49
A51: =RANK(M51,$M$2:$M$6943) | B51: 中国語圏 | C51: 印刷・レイアウト・図枠 | D51: T02,T06,T14 | E51: 図面を開かずに一括処理、図枠の属性を自動更新、属性の抽出・一括編集・Excelとの往復 | F51: ZZML | G51: 批量制作目录—不开图提取块属性 | H51: 図面を開かずに図枠属性を抽出し目録化 | I51: 20 | J51: 14 | K51: 20 | L51: 16 | M51: =SUM(I51:L51) | N51: 非オープン一括目録 | O51: kucha007 | P51: 明经CAD社区 | Q51: 開く | R51: フォーラム添付（ログインが必要な場合あり） | S51: 不明 | U51: W50
A52: =RANK(M52,$M$2:$M$6943) | B52: 英語圏 | C52: ハッチ・面積・長さ集計 | D52: T13 | E52: 図形と数値の連動（フィールド・面積表） | F52: A2F | G52: Areas to Field | H52: 複数面積の合計をフィールド化 | I52: 18 | J52: 17 | K52: 17 | L52: 17 | M52: =SUM(I52:L52) | N52: 合計面積のフィールド化が秀逸 | O52: Lee Mac | P52: Lee Mac Programming | Q52: 開く | R52: 配布ページからダウンロード | S52: ソース | U52: W51
A53: =RANK(M53,$M$2:$M$6943) | B53: 英語圏 | C53: 画層 | D53: T18,T01 | E53: 画層の自動振り分け・標準化、操作に反応して自動処理（リアクター） | F53: AUTOLAY | G53: AutoLay reactor | H53: 寸法・文字等を自動で指定画層へ | I53: 12 | J53: 18 | K53: 18 | L53: 21 | M53: =SUM(I53:L53) | N53: 標準にもレイヤ自動あり | O53: CAD Studio | P53: CAD Studio | Q53: 開く | R53: 配布ページからダウンロード | S53: ソース/暗号化（.vlx）混在 | U53: W52
A54: =RANK(M54,$M$2:$M$6943) | B54: GitHub | C54: 表・Excel連携 | D54: T16 | E54: 数量拾い・集計表 | F54: haws-tally | G54: CNM Tally | H54: 複数図面の注記数量を集計表へ | I54: 22 | J54: 16 | K54: 21 | L54: 10 | M54: =SUM(I54:L54) | N54: 複数図面の注記数量集計 | O54: Thomas Gail Haws | P54: GitHub: hawstom/cnm | Q54: 開く | R54: GitHub（一括取得可） | S54: ソース | U54: W53
A55: =RANK(M55,$M$2:$M$6943) | B55: 英語圏 | C55: 外部参照・図面管理・一括処理 | D55: T02 | E55: 図面を開かずに一括処理 | F55: DBXSCANBLOCKS | G55: DBXscanBlocks | H55: 図面群から指定ブロックを検索 | I55: 18 | J55: 16 | K55: 18 | L55: 17 | M55: =SUM(I55:L55) | N55: 図面を開かずブロック検索 | O55: CAD Studio | P55: CAD Studio | Q55: 開く | R55: 配布ページからダウンロード | S55: ソース/暗号化（.vlx）混在 | U55: W54
A56: =RANK(M56,$M$2:$M$6943) | B56: GitHub | C56: 引出線・注記 | D56: T11,T21 | E56: 文字の重なりを自動で避ける・整列、動かしながら確認できる編集（動的プレビュー） | F56: MSA7 / MLEADERSMARTALIGN | G56: MLeaderSmartAlign | H56: マルチ引出線をライブプレビューで整列 | I56: 20 | J56: 20 | K56: 14 | L56: 15 | M56: =SUM(I56:L56) | N56: ライブプレビュー整列が秀逸 | O56: ivashinpavel07 | P56: GitHub: ivashinpavel07/AutoCAD-AutoLISP-MLeaderSmartAlign | Q56: 開く | R56: GitHub（一括取得可） | S56: ソース | U56: W55
A57: =RANK(M57,$M$2:$M$6943) | B57: 英語圏 | C57: 外部参照・図面管理・一括処理 | D57: T03 | E57: 複数図面へのスクリプト一括実行 | F57: CDC / ODC | G57: OpenDwgsCmds | H57: 開いた全図面でコマンド実行 | I57: 19 | J57: 15 | K57: 17 | L57: 18 | M57: =SUM(I57:L57) | N57: 開いた全図面でコマンド実行 | O57: Terry Miller | P57: AutoLISP Exchange | Q57: 開く | R57: ファイルを直接ダウンロード | S57: ソース | U57: W56
A58: =RANK(M58,$M$2:$M$6943) | B58: 英語圏 | C58: 寸法 | D58: T07 | E58: 検図：寸法値の手入力上書きを検出 | F58: ODC | G58: OverDimCol (ODC) | H58: 文字上書きされた寸法を強調 | I58: 20 | J58: 17 | K58: 14 | L58: 18 | M58: =SUM(I58:L58) | N58: 上書き寸法検出で品質管理 | O58: CAD Studio | P58: CAD Forum | Q58: 開く | R58: 配布ページからダウンロード | S58: ソース/暗号化（.vlx）混在 | U58: W57
... A62: =RANK(M62,$M$2:$M$6943) | B62: 英語圏 | C62: 印刷・レイアウト・図枠 | D62: T17,T05 | E62: 凡例・画層一覧の自動作成、図枠からレイアウト・ビューポートを自動作成 | F62: - | G62: Viewport Legend | H62: ビューポート内の凡例を自動作成（有料） | I62: 21 | J62: 19 | K62: 15 | L62: 14 | M62: =SUM(I62:L62) | N62: VP内凡例自動は斬新 | O62: Tharwat Al Choufi | P62: Tharwat | Q62: 開く | R62: 有料 | S62: 不明 | U62: W61
A63: =RANK(M63,$M$2:$M$6943) | B63: 中国語圏 | C63: 印刷・レイアウト・図枠 | D63: T04 | E63: 図枠の自動認識→一括印刷 | F63: - | G63: 批量打印（图框为图块/矩形/直线） | H63: 多種図枠を認識して一括印刷 | I63: 18 | J63: 12 | K63: 20 | L63: 19 | M63: =SUM(I63:L63) | N63: 図枠認識印刷 | P63: 晓东CAD家园 | Q63: 開く | R63: フォーラム添付（ログインが必要な場合あり） | S63: 不明 | U63: W62
A64: =RANK(M64,$M$2:$M$6943) | B64: 中国語圏 | C64: 文字・テキスト | D64: T15,T21 | E64: 連番の自動記入、動かしながら確認できる編集（動的プレビュー） | F64: 点哪加哪 | G64: 点哪加哪 (@lisp文本) | H64: 文字内の指定桁をクリックで増分コピー | I64: 18 | J64: 17 | K64: 16 | L64: 18 | M64: =SUM(I64:L64) | N64: 桁指定インクリメントが独創的 | O64: VitalGG | P64: @lisp 应用云 | Q64: 開く | R64: 配布ページからダウンロード | S64: ソース（GitHubにも公開） | U64: W63
A65: =RANK(M65,$M$2:$M$6943) | B65: 中国語圏 | C65: 設定・環境 | D65: T28 | E65: 作業環境の保存・復元 | F65: - | G65: 自动输入法（永久免费） | H65: 編集状況に応じ中英IMEを自動切替 | I65: 22 | J65: 18 | K65: 17 | L65: 12 | M65: =SUM(I65:L65) | N65: IME自動切替 | O65: moy838840554 | P65: 明经CAD社区 | Q65: 開く | R65: フォーラム添付（ログインが必要な場合あり） | S65: 不明 | U65: W64
A66: =RANK(M66,$M$2:$M$6943) | B66: 中国語圏 | C66: 選択・絞り込み | D66: その他 | E66: その他 | F66: ss1~ss5 | G66: 选择集记忆 (@lisp选择) | H66: 選択セットを5つまで記憶・再呼出 | I66: 18 | J66: 15 | K66: 16 | L66: 20 | M66: =SUM(I66:L66) | N66: 名前付き選択セット | O66: VitalGG | P66: @lisp 应用云 | Q66: 開く | R66: 配布ページからダウンロード | S66: ソース（GitHubにも公開） | U66: W65
A67: =RANK(M67,$M$2:$M$6943) | B67: 中国語圏 | C67: 線・ポリライン編集 | D67: T21 | E67: 動かしながら確認できる編集（動的プレビュー） | F67: - | G67: 阿甘超级复制V5.0 | H67: 多機能な動的複写 | I67: 17 | J67: 17 | K67: 16 | L67: 19 | M67: =SUM(I67:L67) | N67: 動的複写 | O67: dtucad | P67: 明经CAD社区 | Q67: 開く | R67: フォーラム添付（ログインが必要な場合あり） | S67: 不明 | U67: W66
A68: =RANK(M68,$M$2:$M$6943) | B68: ヨーロッパ | C68: 外部参照・図面管理・一括処理 | D68: T02,T03 | E68: 図面を開かずに一括処理、複数図面へのスクリプト一括実行 | F68: - | G68: ACCORE | H68: accoreconsoleで数百図面にスクリプト/LISPを一括適用 | I68: 19 | J68: 15 | K68: 19 | L68: 15 | M68: =SUM(I68:L68) | N68: コアコンソールで高速一括 | O68: Fraiddd | P68: GitHub: Fraiddd/ACCORE | Q68: 開く | R68: GitHub（一括取得可） | S68: ソース | U68: W67
A69: =RANK(M69,$M$2:$M$6943) | B69: その他の地域 | C69: 印刷・レイアウト・図枠 | D69: T05 | E69: 図枠からレイアウト・ビューポートを自動作成 | F69: AUTOLAMINAS | G69: AUTOLAMINAS | H69: モデルの図枠を走査し各レイアウトにVP自動作成 | I69: 22 | J69: 16 | K69: 18 | L69: 12 | M69: =SUM(I69:L69) | N69: 図枠走査でVP自動作成 | O69: Erick Holger Perez Mescco | P69: GitHub: erickholger2025-sudo/AUTOLISP_AUTOCAD | Q69: 開く | R69: GitHub（一括取得可） | S69: ソース | U69: W68
A70: =RANK(M70,$M$2:$M$6943) | B70: ヨーロッパ | C70: 外部参照・図面管理・一括処理 | D70: T02,T16 | E70: 図面を開かずに一括処理、数量拾い・集計表 | F70: - | G70: odbx_get* | H70: 未オープンの多数図面から画層一覧・ブロック数・ポリ長さ等を抽出 | I70: 20 | J70: 15 | K70: 18 | L70: 15 | M70: =SUM(I70:L70) | N70: 図面を開かず情報抽出 | O70: Fraiddd | P70: GitHub: Fraiddd/ODBX_LIB | Q70: 開く | R70: GitHub（一括取得可） | S70: ソース | U70: W69
A71: =RANK(M71,$M$2:$M$6943) | B71: ヨーロッパ | C71: ハッチ・面積・長さ集計 | D71: T13 | E71: 図形と数値の連動（フィールド・面積表） | F71: totalarea / areaupd / areaedit | G71: TotalArea | H71: リンクした図形群の合計面積を属性に動的表示 | I71: 19 | J71: 20 | K71: 16 | L71: 13 | M71: =SUM(I71:L71) | N71: 面積をリアクタで自動更新 | O71: (gile) | P71: gileCAD | Q71: 開く | R71: 配布ページからダウンロード | S71: ソース | U71: W70
A72: =RANK(M72,$M$2:$M$6943) | B72: 中国語圏 | C72: 文字・テキスト | D72: T12 | E72: 文字の一括検索・置換 | F72: QE | G72: ZW工具 QE 剪贴板批量替换文字 | H72: クリップボードの行で選択文字を順に置換 | I72: 20 | J72: 17 | K72: 16 | L72: 15 | M72: =SUM(I72:L72) | N72: Excel列を図面へ流込 | O72: y1991427360s | P72: GitHub: y1991427360s/zwcad-autolisp-tools | Q72: 開く | R72: GitHub（一括取得可） | S72: ソース | U72: W71
A73: =RANK(M73,$M$2:$M$6943) | B73: ベトナム・東南アジア | C73: 画層 | D73: T01,T18 | E73: 操作に反応して自動処理（リアクター）、画層の自動振り分け・標準化 | F73: - | G73: Ứng dụng REACTOR trong quản lý bản vẽ theo layer | H73: リアクタで作図画層を自動管理 | I73: 19 | J73: 20 | K73: 13 | L73: 16 | M73: =SUM(I73:L73) | N73: 画層をリアクタで自動管理 | O73: CADViet member | P73: CADViet | Q73: 開く | R73: フォーラム添付（ログインが必要な場合あり） | S73: 不明 | U73: W72
A74: =RANK(M74,$M$2:$M$6943) | B74: 中国語圏 | C74: 印刷・レイアウト・図枠 | D74: T04 | E74: 図枠の自動認識→一括印刷 | F74: - | G74: 依云CAD批量打图精灵9.0 | H74: 一括印刷ソフト | I74: 18 | J74: 10 | K74: 20 | L74: 20 | M74: =SUM(I74:L74) | N74: 一括印刷 | O74: 渴望光明88 | P74: 明经CAD社区 | Q74: 開く | R74: フォーラム添付（ログインが必要な場合あり） | S74: 不明 | U74: W73
A75: =RANK(M75,$M$2:$M$6943) | B75: 中国語圏 | C75: 設定・環境 | D75: T28 | E75: 作業環境の保存・復元 | F75: - | G75: 易输入（文字編集時IME自動切替） | H75: 文字編集時に中英IMEを自動切替 | I75: 22 | J75: 18 | K75: 16 | L75: 12 | M75: =SUM(I75:L75) | N75: IME切替 | O75: 红黑墨水 | P75: 明经CAD社区 | Q75: 開く | R75: フォーラム添付（ログインが必要な場合あり） | S75: 不明 | U75: W74
... A77: =RANK(M77,$M$2:$M$6943) | B77: 中国語圏 | C77: 表示・UCS・ビュー | D77: T09 | E77: 新旧図面の差分比較・雲マーク | F77: 阿甘对图器 | G77: 阿甘对图器 | H77: 2図面/ビューポートを同期表示して照合 | I77: 20 | J77: 18 | K77: 14 | L77: 16 | M77: =SUM(I77:L77) | N77: DWGCOMPAREと別の同期照合 | O77: 阿甘(print1985) | P77: @lisp 应用云 | Q77: 開く | R77: 配布ページからダウンロード | S77: ソース（GitHubにも公開） | U77: W76
A78: =RANK(M78,$M$2:$M$6943) | B78: 英語圏 | C78: 寸法 | D78: その他 | E78: その他 | F78: DM | G78: Automatic Dimensions | H78: 直線上の要素を自動寸法記入 | I78: 17 | J78: 16 | K78: 18 | L78: 16 | M78: =SUM(I78:L78) | N78: 直線上要素の自動寸法 | P78: Cadalyst CAD Tips | Q78: 開く | R78: サイト閉鎖・リンク切れ | S78: 不明 | U78: W77
A79: =RANK(M79,$M$2:$M$6943) | B79: 英語圏 | C79: ハッチ・面積・長さ集計 | D79: T13 | E79: 図形と数値の連動（フィールド・面積表） | F79: FAREA, FLENGTH, FPROP | G79: fAREA | H79: 面積・長さの動的ラベル作成 | I79: 19 | J79: 17 | K79: 16 | L79: 15 | M79: =SUM(I79:L79) | N79: 面積長さ動的ラベル | O79: CAD Studio | P79: CAD Forum | Q79: 開く | R79: 配布ページからダウンロード | S79: ソース/暗号化（.vlx）混在 | U79: W78
A80: =RANK(M80,$M$2:$M$6943) | B80: GitHub | C80: 建築 | D80: T24 | E80: 建築：壁・建具・天井割付の作図 | F80: HF | G80: hueflow-elev | H80: 平面から4面展開図外形を自動作図 | I80: 22 | J80: 19 | K80: 19 | L80: 7 | M80: =SUM(I80:L80) | N80: 平面から展開図自動化 | O80: hueflow studio | P80: GitHub: hueflowstudio/hueflow-elev | Q80: 開く | R80: GitHub（一括取得可） | S80: ソース | U80: W79
A81: =RANK(M81,$M$2:$M$6943) | B81: ベトナム・東南アジア | C81: ブロック・属性 | D81: T01,T13 | E81: 操作に反応して自動処理（リアクター）、図形と数値の連動（フィールド・面積表） | F81: - | G81: LISP Ánh xạ giá trị đối tượng | H81: 元値変更で参照先を自動更新(リアクタ) | I81: 22 | J81: 22 | K81: 11 | L81: 12 | M81: =SUM(I81:L81) | N81: リアクタで値を自動連動 | O81: CADViet member | P81: CADViet | Q81: 開く | R81: フォーラム添付（ログインが必要な場合あり） | S81: 不明 | U81: W80
A82: =RANK(M82,$M$2:$M$6943) | B82: ヨーロッパ | C82: 外部参照・図面管理・一括処理 | D82: T02,T18 | E82: 図面を開かずに一括処理、画層の自動振り分け・標準化 | F82: - | G82: odbx_send* | H82: 画層・線種・寸法/文字スタイル・UCS・ビューを複数図面へ配布 | I82: 20 | J82: 14 | K82: 17 | L82: 16 | M82: =SUM(I82:L82) | N82: 標準を複数図面へ配布 | O82: Fraiddd | P82: GitHub: Fraiddd/ODBX_LIB | Q82: 開く | R82: GitHub（一括取得可） | S82: ソース | U82: W81
A83: =RANK(M83,$M$2:$M$6943) | B83: ヨーロッパ | C83: 外部参照・図面管理・一括処理 | D83: T02,T12 | E83: 図面を開かずに一括処理、文字の一括検索・置換 | F83: - | G83: odbx_subst* | H83: 複数図面の文字・MTEXT・属性・ブロック・引出線を一括置換 | I83: 20 | J83: 14 | K83: 18 | L83: 15 | M83: =SUM(I83:L83) | N83: 複数図面の文字一括置換 | O83: Fraiddd | P83: GitHub: Fraiddd/ODBX_LIB | Q83: 開く | R83: GitHub（一括取得可） | S83: ソース | U83: W82
A84: =RANK(M84,$M$2:$M$6943) | B84: 英語圏 | C84: 設定・環境 | D84: その他 | E84: その他 | F84: RRENAME | G84: RRename | H84: 正規表現で名前を一括変更 | I84: 20 | J84: 16 | K84: 15 | L84: 16 | M84: =SUM(I84:L84) | N84: 正規表現で一括改名 | O84: CAD Studio | P84: CAD Forum | Q84: 開く | R84: 配布ページからダウンロード | S84: ソース/暗号化（.vlx）混在 | U84: W83
A85: =RANK(M85,$M$2:$M$6943) | B85: 英語圏 | C85: 文字・テキスト | D85: T12 | E85: 文字の一括検索・置換 | F85: SRXTEXT | G85: srxTEXT | H85: 正規表現で文字を検索置換 | I85: 18 | J85: 16 | K85: 15 | L85: 18 | M85: =SUM(I85:L85) | N85: 正規表現置換は標準に無し | O85: CAD Studio | P85: CAD Forum | Q85: 開く | R85: 配布ページからダウンロード | S85: ソース/暗号化（.vlx）混在 | U85: W84
A86: =RANK(M86,$M$2:$M$6943) | B86: 日本 | C86: 文字・テキスト | D86: T09,T01 | E86: 新旧図面の差分比較・雲マーク、操作に反応して自動処理（リアクター） | F86: - | G86: 修正文字自動赤化 | H86: 修正した文字を自動で赤色に（有料） | I86: 19 | J86: 19 | K86: 14 | L86: 15 | M86: =SUM(I86:L86) | N86: 修正文字を自動で赤化 | O86: ほんだ | P86: note (honda_cadlisp) | Q86: 開く | R86: 有料 | S86: 不明 | U86: W85
A87: =RANK(M87,$M$2:$M$6943) | B87: 中国語圏 | C87: 印刷・レイアウト・図枠 | D87: T04 | E87: 図枠の自動認識→一括印刷 | F87: QQ | G87: 按块打印_v1.7 | H87: ブロック図枠単位で用紙自動適合印刷 | I87: 18 | J87: 12 | K87: 19 | L87: 18 | M87: =SUM(I87:L87) | N87: 図枠ブロック印刷 | O87: kucha007 | P87: 明经CAD社区 | Q87: 開く | R87: フォーラム添付（ログインが必要な場合あり） | S87: 不明 | U87: W86
A88: =RANK(M88,$M$2:$M$6943) | B88: 中国語圏 | C88: 表・Excel連携 | D88: T23 | E88: 分解された表の復元・Excel表の取り込み | F88: 生成表格 | G88: 生成表格 (@lisp文本) | H88: 行列配置の文字からAutoCAD表を生成 | I88: 18 | J88: 14 | K88: 17 | L88: 18 | M88: =SUM(I88:L88) | N88: 文字群→TABLE化 | O88: VitalGG | P88: @lisp 应用云 | Q88: 開く | R88: 配布ページからダウンロード | S88: ソース（GitHubにも公開） | U88: W87
A89: =RANK(M89,$M$2:$M$6943) | B89: 中国語圏 | C89: 設定・環境 | D89: T28 | E89: 作業環境の保存・復元 | F89: 键盘侠 | G89: 键盘侠 | H89: コマンドライン入力時の中英IME自動切替 | I89: 22 | J89: 18 | K89: 17 | L89: 10 | M89: =SUM(I89:L89) | N89: IME自動切替は日本でも有用 | O89: 阿甘 | P89: @lisp 应用云 | Q89: 開く | R89: 配布ページからダウンロード | S89: ソース（GitHubにも公開） | U89: W88
A90: =RANK(M90,$M$2:$M$6943) | B90: 英語圏 | C90: ハッチ・面積・長さ集計 | D90: T16,T13 | E90: 数量拾い・集計表、図形と数値の連動（フィールド・面積表） | F90: AT / AF | G90: Area Label | H90: 面積を表やファイルに書出し | I90: 17 | J90: 13 | K90: 18 | L90: 18 | M90: =SUM(I90:L90) | N90: 面積表・ファイル書出しを一括 | O90: Lee Mac | P90: Lee Mac Programming | Q90: 開く | R90: 配布ページからダウンロード | S90: ソース | U90: W89
A91: =RANK(M91,$M$2:$M$6943) | B91: 英語圏 | C91: 表・Excel連携 | D91: T23 | E91: 分解された表の復元・Excel表の取り込み | F91: B2E | G91: AutoCAD Excel Interface | H91: 範囲内の表文字をExcelへ送る | I91: 18 | J91: 14 | K91: 18 | L91: 16 | M91: =SUM(I91:L91) | N91: 図面上の表文字をExcel化 | P91: Cadalyst CAD Tips | Q91: 開く | R91: サイト閉鎖・リンク切れ | S91: 不明 | U91: W90
A92: =RANK(M92,$M$2:$M$6943) | B92: 日本 | C92: 外部参照・図面管理・一括処理 | D92: T03 | E92: 複数図面へのスクリプト一括実行 | F92: - | G92: Batch DWG-Commander | H92: 自作LISPを複数図面に一括適用（有料） | I92: 16 | J92: 13 | K92: 20 | L92: 17 | M92: =SUM(I92:L92) | N92: 自作LISPを多図面に一括適用 | O92: チコ | P92: note (chiko_root) | Q92: 開く | R92: 有料 | S92: 不明 | U92: W91
A93: =RANK(M93,$M$2:$M$6943) | B93: 中国語圏 | C93: 外部参照・図面管理・一括処理 | D93: T02,T10 | E93: 図面を開かずに一括処理、図面の健全性チェック・お掃除 | F93: - | G93: CAD批量清理与版本转换0.2 | H93: 図面を開かず一括PURGE・版変換 | I93: 17 | J93: 10 | K93: 20 | L93: 19 | M93: =SUM(I93:L93) | N93: 非オープン一括清理 | O93: ProgramFancier | P93: 明经CAD社区 | Q93: 開く | R93: フォーラム添付（ログインが必要な場合あり） | S93: 不明 | U93: W92
A94: =RANK(M94,$M$2:$M$6943) | B94: 英語圏 | C94: 外部参照・図面管理・一括処理 | D94: T02 | E94: 図面を開かずに一括処理 | F94: DBXSCANLAYERS | G94: DBXscanLayers | H94: 図面群から指定画層を検索 | I94: 18 | J94: 15 | K94: 17 | L94: 16 | M94: =SUM(I94:L94) | N94: 図面を開かず画層検索 | O94: CAD Studio | P94: CAD Studio | Q94: 開く | R94: 配布ページからダウンロード | S94: ソース/暗号化（.vlx）混在 | U94: W93
A95: =RANK(M95,$M$2:$M$6943) | B95: 英語圏 | C95: ハッチ・面積・長さ集計 | D95: T13 | E95: 図形と数値の連動（フィールド・面積表） | F95: DYNAREA | G95: DynArea | H95: 動的な面積ラベルを作成 | I95: 19 | J95: 17 | K95: 15 | L95: 15 | M95: =SUM(I95:L95) | N95: 動的面積ラベル | O95: CAD Studio | P95: CAD Forum | Q95: 開く | R95: 配布ページからダウンロード | S95: ソース/暗号化（.vlx）混在 | U95: W94
A96: =RANK(M96,$M$2:$M$6943) | B96: 英語圏 | C96: 表・Excel連携 | D96: T23 | E96: 分解された表の復元・Excel表の取り込み | F96: TE | G96: Export Table of Lines and Text to Excel | H96: 線と文字の表をExcelへ出力 | I96: 18 | J96: 14 | K96: 18 | L96: 16 | M96: =SUM(I96:L96) | N96: 線文字の表をExcel出力 | P96: Cadalyst CAD Tips | Q96: 開く | R96: サイト閉鎖・リンク切れ | S96: 不明 | U96: W95
A97: =RANK(M97,$M$2:$M$6943) | B97: 英語圏 | C97: 文字・テキスト | D97: T12 | E97: 文字の一括検索・置換 | F97: GRSELNUM | G97: GrSelNum | H97: 選択文字中の数値を合計 | I97: 19 | J97: 14 | K97: 15 | L97: 18 | M97: =SUM(I97:L97) | N97: 数値合計は標準に無し | O97: CAD Studio | P97: CAD Forum | Q97: 開く | R97: 配布ページからダウンロード | S97: ソース/暗号化（.vlx）混在 | U97: W96
A98: =RANK(M98,$M$2:$M$6943) | B98: 英語圏 | C98: 文字・テキスト | D98: T15 | E98: 連番の自動記入 | F98: - | G98: Increment | H98: 文字・属性の値を連番増分 | I98: 14 | J98: 13 | K98: 19 | L98: 20 | M98: =SUM(I98:L98) | N98: 連番増分は頻用で実用的 | O98: Gilles Chanteau | P98: Autodesk App Store | Q98: 開く | R98: アプリストア経由（Autodeskアカウントが必要） | S98: 暗号化・インストーラ | U98: W97
A99: =RANK(M99,$M$2:$M$6943) | B99: ヨーロッパ | C99: 文字・テキスト | D99: T15 | E99: 連番の自動記入 | F99: incr / inctxt / incatt / incsuf / incsel / incadd | G99: Increment | H99: 文字・属性の数値/英字を連番増分して配置・更新 | I99: 13 | J99: 13 | K99: 19 | L99: 21 | M99: =SUM(I99:L99) | N99: 連番入力の定番 | O99: (gile) | P99: gileCAD | Q99: 開く | R99: 配布ページからダウンロード | S99: ソース | U99: W98
A100: =RANK(M100,$M$2:$M$6943) | B100: 英語圏 | C100: 文字・テキスト | D100: T13 | E100: 図形と数値の連動（フィールド・面積表） | F100: LINKTEXT | G100: LinkText | H100: 文字同士を連動させる | I100: 20 | J100: 20 | K100: 12 | L100: 14 | M100: =SUM(I100:L100) | N100: 文字同士の連動 | O100: CAD Studio | P100: CAD Studio | Q100: 開く | R100: 配布ページからダウンロード | S100: ソース/暗号化（.vlx）混在 | U100: W99
A101: =RANK(M101,$M$2:$M$6943) | B101: ベトナム・東南アジア | C101: 構造・鉄骨・機械 | D101: T16,T24 | E101: 数量拾い・集計表、建築：壁・建具・天井割付の作図 | F101: sxCAD | G101: Lisp bóc tách khối lượng xây dựng từ mặt bằng Kiến trúc kết cấu | H101: 図面から建築数量を自動拾い（有料） | I101: 21 | J101: 16 | K101: 20 | L101: 9 | M101: =SUM(I101:L101) | N101: 図面から数量自動拾い | O101: AJS / AutoLISP Thật là đơn giản | P101: lisp.vn (AutoLISP Reviewer) | Q101: 開く | R101: 有料 | S101: 不明 | U101: W100
A102: =RANK(M102,$M$2:$M$6943) | B102: ベトナム・東南アジア | C102: 表・Excel連携 | D102: T23,T30 | E102: 分解された表の復元・Excel表の取り込み、AI・OCR・翻訳など新技術との連携 | F102: I2D | G102: Lisp đọc bảng biểu OLE bị mất link | H102: OLE表をOCRで図形化 | I102: 22 | J102: 20 | K102: 12 | L102: 12 | M102: =SUM(I102:L102) | N102: OLE表をOCRで復元 | O102: AJS / AutoLISP Thật là đơn giản | P102: lisp.vn (AutoLISP Reviewer) | Q102: 開く | R102: 配布ページからダウンロード | S102: 不明 | U102: W101
A103: =RANK(M103,$M$2:$M$6943) | B103: 日本 | C103: 線・ポリライン編集 | D103: T08 | E103: 検図：わずかなずれ・隙間・重なりを検出 | F103: - | G103: Maruku DWG-Noise | H103: 微細な座標ズレを一括補正（有料） | I103: 19 | J103: 16 | K103: 15 | L103: 16 | M103: =SUM(I103:L103) | N103: 微細な座標ズレを自動補正 | O103: チコ | P103: note (chiko_root) | Q103: 開く | R103: 有料 | S103: 不明 | U103: W102
A104: =RANK(M104,$M$2:$M$6943) | B104: GitHub | C104: 引出線・注記 | D104: T11 | E104: 文字の重なりを自動で避ける・整列 | F104: MSAP | G104: MLeaderSmartAlignPerimeter | H104: 引出線を外周に沿って配置 | I104: 22 | J104: 20 | K104: 12 | L104: 12 | M104: =SUM(I104:L104) | N104: 引出線を外周配置、新鮮 | O104: ivashinpavel07 | P104: GitHub: ivashinpavel07/AutoCAD-AutoLISP-MLeaderSmartAlign | Q104: 開く | R104: GitHub（一括取得可） | S104: ソース | U104: W103
A105: =RANK(M105,$M$2:$M$6943) | B105: 英語圏 | C105: 設定・環境 | D105: T01 | E105: 操作に反応して自動処理（リアクター） | F105: PRESAVE | G105: PreSave reactor | H105: 保存前に自動処理を実行 | I105: 18 | J105: 19 | K105: 13 | L105: 16 | M105: =SUM(I105:L105) | N105: 保存前自動処理リアクタ | O105: CAD Studio | P105: CAD Studio | Q105: 開く | R105: 配布ページからダウンロード | S105: ソース/暗号化（.vlx）混在 | U105: W104
A106: =RANK(M106,$M$2:$M$6943) | B106: 英語圏 | C106: 設定・環境 | D106: その他 | E106: その他 | F106: RENAMECSV | G106: RenameCSV | H106: CSV表で名前を一括変更 | I106: 19 | J106: 13 | K106: 17 | L106: 17 | M106: =SUM(I106:L106) | N106: CSVで名前を一括変更 | O106: CAD Studio | P106: CAD Forum | Q106: 開く | R106: 配布ページからダウンロード | S106: ソース/暗号化（.vlx）混在 | U106: W105
A107: =RANK(M107,$M$2:$M$6943) | B107: ヨーロッパ | C107: 外部参照・図面管理・一括処理 | D107: T03 | E107: 複数図面へのスクリプト一括実行 | F107: scriptor | G107: SCRIPTOR | H107: サブフォルダ含む全図面にスクリプト/LISPを一括実行 | I107: 16 | J107: 12 | K107: 20 | L107: 18 | M107: =SUM(I107:L107) | N107: フォルダ一括処理の定番 | O107: Patrick_35 | P107: CADxp (Patrick_35) | Q107: 開く | R107: サイト閉鎖・リンク切れ | S107: ソース | U107: W106
A108: =RANK(M108,$M$2:$M$6943) | B108: 英語圏 | C108: 文字・テキスト | D108: T15 | E108: 連番の自動記入 | F108: - | G108: Sequential Numbering Systems | H108: 連番記入システム | I108: 15 | J108: 13 | K108: 19 | L108: 19 | M108: =SUM(I108:L108) | N108: 連番記入システムは頻用 | P108: Cadalyst CAD Tips | Q108: 開く | R108: サイト閉鎖・リンク切れ | S108: 不明 | U108: W107
A109: =RANK(M109,$M$2:$M$6943) | B109: ヨーロッパ | C109: ハッチ・面積・長さ集計 | D109: T13 | E109: 図形と数値の連動（フィールド・面積表） | F109: totalperim / perimupd | G109: TotalPerim | H109: リンクした図形群の合計長さを属性に動的表示 | I109: 19 | J109: 19 | K109: 15 | L109: 13 | M109: =SUM(I109:L109) | N109: 長さを属性に自動連動 | O109: (gile) | P109: gileCAD | Q109: 開く | R109: 配布ページからダウンロード | S109: ソース | U109: W108
A110: =RANK(M110,$M$2:$M$6943) | B110: 英語圏 | C110: 印刷・レイアウト・図枠 | D110: T06 | E110: 図枠の属性を自動更新 | F110: utb | G110: Update Titleblock Attributes | H110: 図枠属性を自動更新 | I110: 17 | J110: 14 | K110: 18 | L110: 17 | M110: =SUM(I110:L110) | N110: 図枠属性を自動更新 | O110: Lee Mac | P110: Lee Mac Programming | Q110: 開く | R110: 配布ページからダウンロード | S110: ソース | U110: W109
A111: =RANK(M111,$M$2:$M$6943) | B111: 中国語圏 | C111: ブロック・属性 | D111: T15,T14 | E111: 連番の自動記入、属性の抽出・一括編集・Excelとの往復 | F111: @block:set-number | G111: 块自动编号 (@lisp Block) | H111: 属性ブロックを上→下・左→右に自動採番 | I111: 18 | J111: 12 | K111: 18 | L111: 18 | M111: =SUM(I111:L111) | N111: 位置順の自動採番 | O111: VitalGG | P111: @lisp 应用云 | Q111: 開く | R111: 配布ページからダウンロード | S111: ソース（GitHubにも公開） | U111: W110
A112: =RANK(M112,$M$2:$M$6943) | B112: 中国語圏 | C112: 外部参照・図面管理・一括処理 | D112: T10,T02 | E112: 図面の健全性チェック・お掃除、図面を開かずに一括処理 | F112: BatPurgeAll | G112: 超级批量清理磁盘DWG | H112: ディスク上の多数DWGを一括清理 | I112: 17 | J112: 10 | K112: 20 | L112: 19 | M112: =SUM(I112:L112) | N112: 非オープン一括清理 | P112: 晓东CAD家园 | Q112: 開く | R112: フォーラム添付（ログインが必要な場合あり） | S112: 不明 | U112: W111
A113: =RANK(M113,$M$2:$M$6943) | B113: GitHub | C113: 外部参照・図面管理・一括処理 | D113: T03 | E113: 複数図面へのスクリプト一括実行 | F113: scripter | G113: batch process | H113: フォルダ内図面をスクリプト一括処理 | I113: 16 | J113: 12 | K113: 19 | L113: 18 | M113: =SUM(I113:L113) | N113: 図面一括スクリプト処理 | O113: Christopher Brisco | P113: GitHub: A-Nony-Mus/Autolisp-Utilities | Q113: 開く | R113: GitHub（一括取得可） | S113: ソース | U113: W112
A114: =RANK(M114,$M$2:$M$6943) | B114: 英語圏 | C114: 外部参照・図面管理・一括処理 | D114: T03 | E114: 複数図面へのスクリプト一括実行 | F114: BatchLisp | G114: BatchLisp | H114: LISPを複数図面で一括実行 | I114: 17 | J114: 12 | K114: 19 | L114: 17 | M114: =SUM(I114:L114) | N114: LISPを複数図面で一括実行 | O114: Jeffery P. Sanders | P114: JefferyPSanders.com | Q114: 開く | R114: 配布ページからダウンロード | S114: 不明 | U114: W113
A115: =RANK(M115,$M$2:$M$6943) | B115: 中国語圏 | C115: 設備 | D115: T26,T16,T30 | E115: 設備：器具の自動割付、配線の最短経路、数量拾い・集計表、AI・OCR・翻訳など新技術との連携 | F115: - | G115: cad-cable-stat 电缆长度自动统计 | H115: 配線経路をLISPで抽出しPythonで経路探索・長さ集計 | I115: 22 | J115: 20 | K115: 18 | L115: 5 | M115: =SUM(I115:L115) | N115: ケーブル長自動算定 | O115: y1991427360s | P115: GitHub: y1991427360s/cad-cable-stat | Q115: 開く | R115: GitHub（一括取得可） | S115: ソース | U115: W114
A116: =RANK(M116,$M$2:$M$6943) | B116: 英語圏 | C116: 印刷・レイアウト・図枠 | D116: T06 | E116: 図枠の属性を自動更新 | F116: - | G116: condattupd.lsp | H116: 図枠記入欄を条件付き一括更新 | I116: 16 | J116: 15 | K116: 17 | L116: 17 | M116: =SUM(I116:L116) | N116: 条件付きで図枠一括更新 | O116: Henry C. Francis (ParaCADD) | P116: ParaCADD | Q116: 開く | R116: 配布ページからダウンロード | S116: ソース | U116: W115
A117: =RANK(M117,$M$2:$M$6943) | B117: 英語圏 | C117: 外部参照・図面管理・一括処理 | D117: T03 | E117: 複数図面へのスクリプト一括実行 | F117: c2dwg | G117: Copy to Drawings | H117: 図形を複数図面へコピー | I117: 19 | J117: 14 | K117: 15 | L117: 17 | M117: =SUM(I117:L117) | N117: 図形を複数図面へ複写 | O117: Lee Mac | P117: Lee Mac Programming | Q117: 開く | R117: 配布ページからダウンロード | S117: ソース | U117: W116
A118: =RANK(M118,$M$2:$M$6943) | B118: ロシア語圏 | C118: 11 | D118: T04,T05 | E118: 図枠の自動認識→一括印刷、図枠からレイアウト・ビューポートを自動作成 | F118: FF / FFPLOT / FFLAYOUT | G118: FrameFinder | H118: モデル空間のGOST図枠を検出し一括印刷/レイアウト化 | I118: 20 | J118: 15 | K118: 20 | L118: 10 | M118: =SUM(I118:L118) | N118: 図枠自動検出で一括印刷 | O118: SkeletonTM | P118: GitHub: SkeletonTM/FrameFinder | Q118: 開く | R118: GitHub（一括取得可） | S118: ソース | U118: W117
A119: =RANK(M119,$M$2:$M$6943) | B119: 英語圏 | C119: 線・ポリライン編集 | D119: T08 | E119: 検図：わずかなずれ・隙間・重なりを検出 | F119: GAPS | G119: Gaps | H119: 線の隙間・端点の未接続を表示 | I119: 19 | J119: 15 | K119: 16 | L119: 15 | M119: =SUM(I119:L119) | N119: 隙間・未接続を可視化 | O119: CAD Studio | P119: CAD Forum | Q119: 開く | R119: 配布ページからダウンロード | S119: ソース/暗号化（.vlx）混在 | T119: CADblocos / Aprender CAD | U119: W118
A120: =RANK(M120,$M$2:$M$6943) | B120: GitHub | C120: 建築 | D120: T24 | E120: 建築：壁・建具・天井割付の作図 | F120: GENBLOCK | G120: GENBLOCK | H120: 住宅区画ブロック（道路・番号付）を自動生成 | I120: 21 | J120: 16 | K120: 20 | L120: 8 | M120: =SUM(I120:L120) | N120: 住宅区画自動生成、計画限定 | O120: vjspab | P120: GitHub: vjspab/autocad-lisp-toolkit | Q120: 開く | R120: GitHub（一括取得可） | S120: ソース | T120: GitHub: vjspab/autocad-lisp-toolkit | U120: W119
A121: =RANK(M121,$M$2:$M$6943) | B121: ベトナム・東南アジア | C121: 文字・テキスト | D121: T13 | E121: 図形と数値の連動（フィールド・面積表） | F121: - | G121: Lisp các phép tính đại số tự động cập nhật | H121: 数値文字の計算式を自動再計算 | I121: 21 | J121: 21 | K121: 11 | L121: 12 | M121: =SUM(I121:L121) | N121: 計算式の自動再計算 | O121: CADViet member | P121: CADViet | Q121: 開く | R121: フォーラム添付（ログインが必要な場合あり） | S121: 不明 | U121: W120
A122: =RANK(M122,$M$2:$M$6943) | B122: 英語圏 | C122: 表・Excel連携 | D122: T14,T23,T12 | E122: 属性の抽出・一括編集・Excelとの往復、分解された表の復元・Excel表の取り込み、文字の一括検索・置換 | F122: LOOKUPXLS | G122: LookupXLS | H122: Excel表で文字・属性を照合置換 | I122: 20 | J122: 16 | K122: 16 | L122: 13 | M122: =SUM(I122:L122) | N122: Excel表で照合置換 | O122: CAD Studio | P122: CAD Studio | Q122: 開く | R122: 配布ページからダウンロード | S122: ソース/暗号化（.vlx）混在 | U122: W121
A123: =RANK(M123,$M$2:$M$6943) | B123: ヨーロッパ | C123: 表・Excel連携 | D123: T14,T23 | E123: 属性の抽出・一括編集・Excelとの往復、分解された表の復元・Excel表の取り込み | F123: lxl / explxl / implxl | G123: LXL | H123: 属性・文字をExcelセルと双方向リンク | I123: 18 | J123: 16 | K123: 17 | L123: 14 | M123: =SUM(I123:L123) | N123: Excelと双方向リンク | O123: Patrick_35 | P123: CADxp (Patrick_35) | Q123: 開く | R123: サイト閉鎖・リンク切れ | S123: ソース | U123: W122
A124: =RANK(M124,$M$2:$M$6943) | B124: 英語圏 | C124: 設定・環境 | D124: T28 | E124: 作業環境の保存・復元 | F124: RETEMPLATE | G124: ReTemplate | H124: 変更したテンプレートを図面に適用 | I124: 18 | J124: 14 | K124: 17 | L124: 16 | M124: =SUM(I124:L124) | N124: テンプレート変更を既存図に | O124: CAD Studio | P124: CAD Studio | Q124: 開く | R124: 配布ページからダウンロード | S124: ソース/暗号化（.vlx）混在 | U124: W123
A125: =RANK(M125,$M$2:$M$6943) | B125: 中国語圏 | C125: 座標・測量・土木 | D125: T27 | E125: 測量・土木：座標・レベル・縦断 | F125: TF-CALC | G125: TerrainForge 方格网土方计算 | H125: TIN＋方眼法で造成土量計算・表出力 | I125: 22 | J125: 16 | K125: 19 | L125: 8 | M125: =SUM(I125:L125) | N125: 土量計算を図面内完結 | O125: leileistart | P125: GitHub: leileistart/TerrainForge | Q125: 開く | R125: GitHub（一括取得可） | S125: ソース | U125: W124
A126: =RANK(M126,$M$2:$M$6943) | B126: GitHub | C126: 建築 | D126: T24 | E126: 建築：壁・建具・天井割付の作図 | F126: WCL | G126: WallCenterline | H126: 平面図の壁中心線を自動生成 | I126: 22 | J126: 18 | K126: 17 | L126: 8 | M126: =SUM(I126:L126) | N126: 壁中心線自動生成 | O126: beastt1992 | P126: GitHub: beastt1992/WallCenterline | Q126: 開く | R126: GitHub（一括取得可） | S126: ソース | U126: W125
A127: =RANK(M127,$M$2:$M$6943) | B127: ロシア語圏 | C127: 10 | D127: T23 | E127: 分解された表の復元・Excel表の取り込み | F127: PRIM2TABLE | G127: Сборка(восстановление) «взорванных» таблиц и передача(экспорт) таблиц в Exce - PRIM2TABLE | H127: 分解された表を復元しExcel出力 | I127: 20 | J127: 16 | K127: 16 | L127: 13 | M127: =SUM(I127:L127) | N127: 分解表を表に復元 | O127: dr_t_j | P127: dwg.ru | Q127: 開く | R127: ログイン・会員登録が必要 | S127: 不明 | U127: W126
A128: =RANK(M128,$M$2:$M$6943) | B128: 中国語圏 | C128: 文字・テキスト | D128: T12 | E128: 文字の一括検索・置換 | F128: - | G128: 对话框文字万能替换（正则） | H128: 正規表現対応の文字一括置換 | I128: 16 | J128: 14 | K128: 16 | L128: 19 | M128: =SUM(I128:L128) | N128: 正規表現置換 | P128: 晓东CAD家园 | Q128: 開く | R128: フォーラム添付（ログインが必要な場合あり） | S128: 不明 | U128: W127
A129: =RANK(M129,$M$2:$M$6943) | B129: 中国語圏 | C129: 表・Excel連携 | D129: T23 | E129: 分解された表の復元・Excel表の取り込み | F129: 行列计算 | G129: 行列计算 (@lisp数学) | H129: 表状に並んだ文字数値を行列ごとに計算 | I129: 20 | J129: 15 | K129: 15 | L129: 15 | M129: =SUM(I129:L129) | N129: 図中の表を計算可能に | O129: VitalGG | P129: @lisp 应用云 | Q129: 開く | R129: 配布ページからダウンロード | S129: ソース（GitHubにも公開） | U129: W128
A130: =RANK(M130,$M$2:$M$6943) | B130: 英語圏 | C130: 文字・テキスト | D130: T12 | E130: 文字の一括検索・置換 | F130: ADDME | G130: AddMe | H130: 選択文字の数値を合計 | I130: 19 | J130: 12 | K130: 15 | L130: 18 | M130: =SUM(I130:L130) | N130: 数値合計は標準に無し | O130: CAD Studio | P130: CAD Studio | Q130: 開く | R130: 配布ページからダウンロード | S130: ソース/暗号化（.vlx）混在 | U130: W129
A131: =RANK(M131,$M$2:$M$6943) | B131: 英語圏 | C131: 外部参照・図面管理・一括処理 | D131: T12,T03 | E131: 文字の一括検索・置換、複数図面へのスクリプト一括実行 | F131: - | G131: Adjust Text for All Drawings in a Directory | H131: フォルダ内全図面の文字を一括調整 | I131: 18 | J131: 12 | K131: 19 | L131: 15 | M131: =SUM(I131:L131) | N131: 図面を開かず文字一括調整 | P131: Cadalyst CAD Tips | Q131: 開く | R131: サイト閉鎖・リンク切れ | S131: 不明 | U131: W130
A132: =RANK(M132,$M$2:$M$6943) | B132: 中国語圏 | C132: その他 | D132: T30 | E132: AI・OCR・翻訳など新技術との連携 | F132: 生成内容/图纸审查 | G132: AIGC | H132: ローカルLLM(Ollama)で文章生成・図面審査 | I132: 22 | J132: 22 | K132: 8 | L132: 12 | M132: =SUM(I132:L132) | N132: CAD内LLM連携 | O132: VitalGG | P132: @lisp 应用云 | Q132: 開く | R132: 配布ページからダウンロード | S132: ソース（GitHubにも公開） | U132: W131
A133: =RANK(M133,$M$2:$M$6943) | B133: 英語圏 | C133: 文字・テキスト | D133: T22,T01 | E133: 曲線に沿った文字・図形の配置、操作に反応して自動処理（リアクター） | F133: DTCurve / DTRemove | G133: Align Text to Curve (Auto Re-align) | H133: 曲線沿い文字を自動再配置 | I133: 20 | J133: 22 | K133: 10 | L133: 12 | M133: =SUM(I133:L133) | N133: リアクタで自動再配置 | O133: Lee Mac | P133: Lee Mac Programming | Q133: 開く | R133: 配布ページからダウンロード | S133: ソース | U133: W132
A134: =RANK(M134,$M$2:$M$6943) | B134: 英語圏 | C134: ハッチ・面積・長さ集計 | D134: T13,T16 | E134: 図形と数値の連動（フィールド・面積表）、数量拾い・集計表 | F134: AREATBL | G134: AreaTable.lsp | H134: 面積ラベルと集計表を作成 | I134: 16 | J134: 13 | K134: 17 | L134: 18 | M134: =SUM(I134:L134) | N134: 面積ラベルと集計表を一括作成 | O134: CADAuthority | P134: CAD Authority | Q134: 開く | R134: 配布ページからダウンロード | S134: 不明 | T134: CADthèque | U134: W133
A135: =RANK(M135,$M$2:$M$6943) | B135: 英語圏 | C135: ブロック・属性 | D135: T15,T14 | E135: 連番の自動記入、属性の抽出・一括編集・Excelとの往復 | F135: ATTINC | G135: ATTINC | H135: 属性値を連番で増加 | I135: 16 | J135: 13 | K135: 18 | L135: 17 | M135: =SUM(I135:L135) | N135: 属性の自動連番 | O135: Jeffery P. Sanders | P135: JefferyPSanders.com | Q135: 開く | R135: 配布ページからダウンロード | S135: 不明 | U135: W134
...

Sheet テーマ別集計
A1: テーマ | B1: テーマ名 | C1: 関連件数 | D1: うち70点以上 | E1: GitHub（一括取得可） | F1: ファイルを直接ダウンロード | G1: 配布ページからダウンロード | H1: ページ内にコード掲載 | I1: フォーラム添付（ログインが必要な場合あり） | J1: ログイン・会員登録が必要 | K1: 有料 | L1: アプリストア経由（Autodeskアカウントが必要） | M1: アクセス制限あり | N1: サイト閉鎖・リンク切れ
A2: その他 | B2: その他 | C2: =COUNTIF(総合一覧!$D$2:$D$6943,"*"&A2&"*") | D2: =COUNTIFS(総合一覧!$D$2:$D$6943,"*"&A2&"*",総合一覧!$M$2:$M$6943,">=70") | E2: =COUNTIFS(総合一覧!$D$2:$D$6943,"*"&$A2&"*",総合一覧!$R$2:$R$6943,E$1) | F2: =COUNTIFS(総合一覧!$D$2:$D$6943,"*"&$A2&"*",総合一覧!$R$2:$R$6943,F$1) | G2: =COUNTIFS(総合一覧!$D$2:$D$6943,"*"&$A2&"*",総合一覧!$R$2:$R$6943,G$1) | H2: =COUNTIFS(総合一覧!$D$2:$D$6943,"*"&$A2&"*",総合一覧!$R$2:$R$6943,H$1) | I2: =COUNTIFS(総合一覧!$D$2:$D$6943,"*"&$A2&"*",総合一覧!$R$2:$R$6943,I$1) | J2: =COUNTIFS(総合一覧!$D$2:$D$6943,"*"&$A2&"*",総合一覧!$R$2:$R$6943,J$1) | K2: =COUNTIFS(総合一覧!$D$2:$D$6943,"*"&$A2&"*",総合一覧!$R$2:$R$6943,K$1) | L2: =COUNTIFS(総合一覧!$D$2:$D$6943,"*"&$A2&"*",総合一覧!$R$2:$R$6943,L$1) | ... N2: =COUNTIFS(総合一覧!$D$2:$D$6943,"*"&$A2&"*",総合一覧!$R$2:$R$6943,N$1)
A3: T01 | B3: 操作に反応して自動処理（リアクター） | C3: =COUNTIF(総合一覧!$D$2:$D$6943,"*"&A3&"*") | D3: =COUNTIFS(総合一覧!$D$2:$D$6943,"*"&A3&"*",総合一覧!$M$2:$M$6943,">=70") | E3: =COUNTIFS(総合一覧!$D$2:$D$6943,"*"&$A3&"*",総合一覧!$R$2:$R$6943,E$1) | F3: =COUNTIFS(総合一覧!$D$2:$D$6943,"*"&$A3&"*",総合一覧!$R$2:$R$6943,F$1) | G3: =COUNTIFS(総合一覧!$D$2:$D$6943,"*"&$A3&"*",総合一覧!$R$2:$R$6943,G$1) | H3: =COUNTIFS(総合一覧!$D$2:$D$6943,"*"&$A3&"*",総合一覧!$R$2:$R$6943,H$1) | I3: =COUNTIFS(総合一覧!$D$2:$D$6943,"*"&$A3&"*",総合一覧!$R$2:$R$6943,I$1) | J3: =COUNTIFS(総合一覧!$D$2:$D$6943,"*"&$A3&"*",総合一覧!$R$2:$R$6943,J$1) | K3: =COUNTIFS(総合一覧!$D$2:$D$6943,"*"&$A3&"*",総合一覧!$R$2:$R$6943,K$1) | L3: =COUNTIFS(総合一覧!$D$2:$D$6943,"*"&$A3&"*",総合一覧!$R$2:$R$6943,L$1) | ... N3: =COUNTIFS(総合一覧!$D$2:$D$6943,"*"&$A3&"*",総合一覧!$R$2:$R$6943,N$1)
A4: T02 | B4: 図面を開かずに一括処理 | C4: =COUNTIF(総合一覧!$D$2:$D$6943,"*"&A4&"*") | D4: =COUNTIFS(総合一覧!$D$2:$D$6943,"*"&A4&"*",総合一覧!$M$2:$M$6943,">=70") | E4: =COUNTIFS(総合一覧!$D$2:$D$6943,"*"&$A4&"*",総合一覧!$R$2:$R$6943,E$1) | F4: =COUNTIFS(総合一覧!$D$2:$D$6943,"*"&$A4&"*",総合一覧!$R$2:$R$6943,F$1) | G4: =COUNTIFS(総合一覧!$D$2:$D$6943,"*"&$A4&"*",総合一覧!$R$2:$R$6943,G$1) | H4: =COUNTIFS(総合一覧!$D$2:$D$6943,"*"&$A4&"*",総合一覧!$R$2:$R$6943,H$1) | I4: =COUNTIFS(総合一覧!$D$2:$D$6943,"*"&$A4&"*",総合一覧!$R$2:$R$6943,I$1) | J4: =COUNTIFS(総合一覧!$D$2:$D$6943,"*"&$A4&"*",総合一覧!$R$2:$R$6943,J$1) | K4: =COUNTIFS(総合一覧!$D$2:$D$6943,"*"&$A4&"*",総合一覧!$R$2:$R$6943,K$1) | L4: =COUNTIFS(総合一覧!$D$2:$D$6943,"*"&$A4&"*",総合一覧!$R$2:$R$6943,L$1) | ... N4: =COUNTIFS(総合一覧!$D$2:$D$6943,"*"&$A4&"*",総合一覧!$R$2:$R$6943,N$1)
A5: T03 | B5: 複数図面へのスクリプト一括実行 | C5: =COUNTIF(総合一覧!$D$2:$D$6943,"*"&A5&"*") | D5: =COUNTIFS(総合一覧!$D$2:$D$6943,"*"&A5&"*",総合一覧!$M$2:$M$6943,">=70") | E5: =COUNTIFS(総合一覧!$D$2:$D$6943,"*"&$A5&"*",総合一覧!$R$2:$R$6943,E$1) | F5: =COUNTIFS(総合一覧!$D$2:$D$6943,"*"&$A5&"*",総合一覧!$R$2:$R$6943,F$1) | G5: =COUNTIFS(総合一覧!$D$2:$D$6943,"*"&$A5&"*",総合一覧!$R$2:$R$6943,G$1) | H5: =COUNTIFS(総合一覧!$D$2:$D$6943,"*"&$A5&"*",総合一覧!$R$2:$R$6943,H$1) | I5: =COUNTIFS(総合一覧!$D$2:$D$6943,"*"&$A5&"*",総合一覧!$R$2:$R$6943,I$1) | J5: =COUNTIFS(総合一覧!$D$2:$D$6943,"*"&$A5&"*",総合一覧!$R$2:$R$6943,J$1) | K5: =COUNTIFS(総合一覧!$D$2:$D$6943,"*"&$A5&"*",総合一覧!$R$2:$R$6943,K$1) | L5: =COUNTIFS(総合一覧!$D$2:$D$6943,"*"&$A5&"*",総合一覧!$R$2:$R$6943,L$1) | ... N5: =COUNTIFS(総合一覧!$D$2:$D$6943,"*"&$A5&"*",総合一覧!$R$2:$R$6943,N$1)
A6: T04 | B6: 図枠の自動認識→一括印刷 | C6: =COUNTIF(総合一覧!$D$2:$D$6943,"*"&A6&"*") | D6: =COUNTIFS(総合一覧!$D$2:$D$6943,"*"&A6&"*",総合一覧!$M$2:$M$6943,">=70") | E6: =COUNTIFS(総合一覧!$D$2:$D$6943,"*"&$A6&"*",総合一覧!$R$2:$R$6943,E$1) | F6: =COUNTIFS(総合一覧!$D$2:$D$6943,"*"&$A6&"*",総合一覧!$R$2:$R$6943,F$1) | G6: =COUNTIFS(総合一覧!$D$2:$D$6943,"*"&$A6&"*",総合一覧!$R$2:$R$6943,G$1) | H6: =COUNTIFS(総合一覧!$D$2:$D$6943,"*"&$A6&"*",総合一覧!$R$2:$R$6943,H$1) | I6: =COUNTIFS(総合一覧!$D$2:$D$6943,"*"&$A6&"*",総合一覧!$R$2:$R$6943,I$1) | J6: =COUNTIFS(総合一覧!$D$2:$D$6943,"*"&$A6&"*",総合一覧!$R$2:$R$6943,J$1) | K6: =COUNTIFS(総合一覧!$D$2:$D$6943,"*"&$A6&"*",総合一覧!$R$2:$R$6943,K$1) | L6: =COUNTIFS(総合一覧!$D$2:$D$6943,"*"&$A6&"*",総合一覧!$R$2:$R$6943,L$1) | ... N6: =COUNTIFS(総合一覧!$D$2:$D$6943,"*"&$A6&"*",総合一覧!$R$2:$R$6943,N$1)
A7: T05 | B7: 図枠からレイアウト・ビューポートを自動作成 | C7: =COUNTIF(総合一覧!$D$2:$D$6943,"*"&A7&"*") | D7: =COUNTIFS(総合一覧!$D$2:$D$6943,"*"&A7&"*",総合一覧!$M$2:$M$6943,">=70") | E7: =COUNTIFS(総合一覧!$D$2:$D$6943,"*"&$A7&"*",総合一覧!$R$2:$R$6943,E$1) | F7: =COUNTIFS(総合一覧!$D$2:$D$6943,"*"&$A7&"*",総合一覧!$R$2:$R$6943,F$1) | G7: =COUNTIFS(総合一覧!$D$2:$D$6943,"*"&$A7&"*",総合一覧!$R$2:$R$6943,G$1) | H7: =COUNTIFS(総合一覧!$D$2:$D$6943,"*"&$A7&"*",総合一覧!$R$2:$R$6943,H$1) | I7: =COUNTIFS(総合一覧!$D$2:$D$6943,"*"&$A7&"*",総合一覧!$R$2:$R$6943,I$1) | J7: =COUNTIFS(総合一覧!$D$2:$D$6943,"*"&$A7&"*",総合一覧!$R$2:$R$6943,J$1) | K7: =COUNTIFS(総合一覧!$D$2:$D$6943,"*"&$A7&"*",総合一覧!$R$2:$R$6943,K$1) | L7: =COUNTIFS(総合一覧!$D$2:$D$6943,"*"&$A7&"*",総合一覧!$R$2:$R$6943,L$1) | ... N7: =COUNTIFS(総合一覧!$D$2:$D$6943,"*"&$A7&"*",総合一覧!$R$2:$R$6943,N$1)
A8: T06 | B8: 図枠の属性を自動更新 | C8: =COUNTIF(総合一覧!$D$2:$D$6943,"*"&A8&"*") | D8: =COUNTIFS(総合一覧!$D$2:$D$6943,"*"&A8&"*",総合一覧!$M$2:$M$6943,">=70") | E8: =COUNTIFS(総合一覧!$D$2:$D$6943,"*"&$A8&"*",総合一覧!$R$2:$R$6943,E$1) | F8: =COUNTIFS(総合一覧!$D$2:$D$6943,"*"&$A8&"*",総合一覧!$R$2:$R$6943,F$1) | G8: =COUNTIFS(総合一覧!$D$2:$D$6943,"*"&$A8&"*",総合一覧!$R$2:$R$6943,G$1) | H8: =COUNTIFS(総合一覧!$D$2:$D$6943,"*"&$A8&"*",総合一覧!$R$2:$R$6943,H$1) | I8: =COUNTIFS(総合一覧!$D$2:$D$6943,"*"&$A8&"*",総合一覧!$R$2:$R$6943,I$1) | J8: =COUNTIFS(総合一覧!$D$2:$D$6943,"*"&$A8&"*",総合一覧!$R$2:$R$6943,J$1) | K8: =COUNTIFS(総合一覧!$D$2:$D$6943,"*"&$A8&"*",総合一覧!$R$2:$R$6943,K$1) | L8: =COUNTIFS(総合一覧!$D$2:$D$6943,"*"&$A8&"*",総合一覧!$R$2:$R$6943,L$1) | ... N8: =COUNTIFS(総合一覧!$D$2:$D$6943,"*"&$A8&"*",総合一覧!$R$2:$R$6943,N$1)
A9: T07 | B9: 検図：寸法値の手入力上書きを検出 | C9: =COUNTIF(総合一覧!$D$2:$D$6943,"*"&A9&"*") | D9: =COUNTIFS(総合一覧!$D$2:$D$6943,"*"&A9&"*",総合一覧!$M$2:$M$6943,">=70") | E9: =COUNTIFS(総合一覧!$D$2:$D$6943,"*"&$A9&"*",総合一覧!$R$2:$R$6943,E$1) | F9: =COUNTIFS(総合一覧!$D$2:$D$6943,"*"&$A9&"*",総合一覧!$R$2:$R$6943,F$1) | G9: =COUNTIFS(総合一覧!$D$2:$D$6943,"*"&$A9&"*",総合一覧!$R$2:$R$6943,G$1) | H9: =COUNTIFS(総合一覧!$D$2:$D$6943,"*"&$A9&"*",総合一覧!$R$2:$R$6943,H$1) | I9: =COUNTIFS(総合一覧!$D$2:$D$6943,"*"&$A9&"*",総合一覧!$R$2:$R$6943,I$1) | J9: =COUNTIFS(総合一覧!$D$2:$D$6943,"*"&$A9&"*",総合一覧!$R$2:$R$6943,J$1) | K9: =COUNTIFS(総合一覧!$D$2:$D$6943,"*"&$A9&"*",総合一覧!$R$2:$R$6943,K$1) | L9: =COUNTIFS(総合一覧!$D$2:$D$6943,"*"&$A9&"*",総合一覧!$R$2:$R$6943,L$1) | ... N9: =COUNTIFS(総合一覧!$D$2:$D$6943,"*"&$A9&"*",総合一覧!$R$2:$R$6943,N$1)
A10: T08 | B10: 検図：わずかなずれ・隙間・重なりを検出 | C10: =COUNTIF(総合一覧!$D$2:$D$6943,"*"&A10&"*") | D10: =COUNTIFS(総合一覧!$D$2:$D$6943,"*"&A10&"*",総合一覧!$M$2:$M$6943,">=70") | E10: =COUNTIFS(総合一覧!$D$2:$D$6943,"*"&$A10&"*",総合一覧!$R$2:$R$6943,E$1) | F10: =COUNTIFS(総合一覧!$D$2:$D$6943,"*"&$A10&"*",総合一覧!$R$2:$R$6943,F$1) | G10: =COUNTIFS(総合一覧!$D$2:$D$6943,"*"&$A10&"*",総合一覧!$R$2:$R$6943,G$1) | H10: =COUNTIFS(総合一覧!$D$2:$D$6943,"*"&$A10&"*",総合一覧!$R$2:$R$6943,H$1) | I10: =COUNTIFS(総合一覧!$D$2:$D$6943,"*"&$A10&"*",総合一覧!$R$2:$R$6943,I$1) | J10: =COUNTIFS(総合一覧!$D$2:$D$6943,"*"&$A10&"*",総合一覧!$R$2:$R$6943,J$1) | K10: =COUNTIFS(総合一覧!$D$2:$D$6943,"*"&$A10&"*",総合一覧!$R$2:$R$6943,K$1) | L10: =COUNTIFS(総合一覧!$D$2:$D$6943,"*"&$A10&"*",総合一覧!$R$2:$R$6943,L$1) | ... N10: =COUNTIFS(総合一覧!$D$2:$D$6943,"*"&$A10&"*",総合一覧!$R$2:$R$6943,N$1)
A11: T09 | B11: 新旧図面の差分比較・雲マーク | C11: =COUNTIF(総合一覧!$D$2:$D$6943,"*"&A11&"*") | D11: =COUNTIFS(総合一覧!$D$2:$D$6943,"*"&A11&"*",総合一覧!$M$2:$M$6943,">=70") | E11: =COUNTIFS(総合一覧!$D$2:$D$6943,"*"&$A11&"*",総合一覧!$R$2:$R$6943,E$1) | F11: =COUNTIFS(総合一覧!$D$2:$D$6943,"*"&$A11&"*",総合一覧!$R$2:$R$6943,F$1) | G11: =COUNTIFS(総合一覧!$D$2:$D$6943,"*"&$A11&"*",総合一覧!$R$2:$R$6943,G$1) | H11: =COUNTIFS(総合一覧!$D$2:$D$6943,"*"&$A11&"*",総合一覧!$R$2:$R$6943,H$1) | I11: =COUNTIFS(総合一覧!$D$2:$D$6943,"*"&$A11&"*",総合一覧!$R$2:$R$6943,I$1) | J11: =COUNTIFS(総合一覧!$D$2:$D$6943,"*"&$A11&"*",総合一覧!$R$2:$R$6943,J$1) | K11: =COUNTIFS(総合一覧!$D$2:$D$6943,"*"&$A11&"*",総合一覧!$R$2:$R$6943,K$1) | L11: =COUNTIFS(総合一覧!$D$2:$D$6943,"*"&$A11&"*",総合一覧!$R$2:$R$6943,L$1) | ... N11: =COUNTIFS(総合一覧!$D$2:$D$6943,"*"&$A11&"*",総合一覧!$R$2:$R$6943,N$1)
A12: T10 | B12: 図面の健全性チェック・お掃除 | C12: =COUNTIF(総合一覧!$D$2:$D$6943,"*"&A12&"*") | D12: =COUNTIFS(総合一覧!$D$2:$D$6943,"*"&A12&"*",総合一覧!$M$2:$M$6943,">=70") | E12: =COUNTIFS(総合一覧!$D$2:$D$6943,"*"&$A12&"*",総合一覧!$R$2:$R$6943,E$1) | F12: =COUNTIFS(総合一覧!$D$2:$D$6943,"*"&$A12&"*",総合一覧!$R$2:$R$6943,F$1) | G12: =COUNTIFS(総合一覧!$D$2:$D$6943,"*"&$A12&"*",総合一覧!$R$2:$R$6943,G$1) | H12: =COUNTIFS(総合一覧!$D$2:$D$6943,"*"&$A12&"*",総合一覧!$R$2:$R$6943,H$1) | I12: =COUNTIFS(総合一覧!$D$2:$D$6943,"*"&$A12&"*",総合一覧!$R$2:$R$6943,I$1) | J12: =COUNTIFS(総合一覧!$D$2:$D$6943,"*"&$A12&"*",総合一覧!$R$2:$R$6943,J$1) | K12: =COUNTIFS(総合一覧!$D$2:$D$6943,"*"&$A12&"*",総合一覧!$R$2:$R$6943,K$1) | L12: =COUNTIFS(総合一覧!$D$2:$D$6943,"*"&$A12&"*",総合一覧!$R$2:$R$6943,L$1) | ... N12: =COUNTIFS(総合一覧!$D$2:$D$6943,"*"&$A12&"*",総合一覧!$R$2:$R$6943,N$1)
A13: T11 | B13: 文字の重なりを自動で避ける・整列 | C13: =COUNTIF(総合一覧!$D$2:$D$6943,"*"&A13&"*") | D13: =COUNTIFS(総合一覧!$D$2:$D$6943,"*"&A13&"*",総合一覧!$M$2:$M$6943,">=70") | E13: =COUNTIFS(総合一覧!$D$2:$D$6943,"*"&$A13&"*",総合一覧!$R$2:$R$6943,E$1) | F13: =COUNTIFS(総合一覧!$D$2:$D$6943,"*"&$A13&"*",総合一覧!$R$2:$R$6943,F$1) | G13: =COUNTIFS(総合一覧!$D$2:$D$6943,"*"&$A13&"*",総合一覧!$R$2:$R$6943,G$1) | H13: =COUNTIFS(総合一覧!$D$2:$D$6943,"*"&$A13&"*",総合一覧!$R$2:$R$6943,H$1) | I13: =COUNTIFS(総合一覧!$D$2:$D$6943,"*"&$A13&"*",総合一覧!$R$2:$R$6943,I$1) | J13: =COUNTIFS(総合一覧!$D$2:$D$6943,"*"&$A13&"*",総合一覧!$R$2:$R$6943,J$1) | K13: =COUNTIFS(総合一覧!$D$2:$D$6943,"*"&$A13&"*",総合一覧!$R$2:$R$6943,K$1) | L13: =COUNTIFS(総合一覧!$D$2:$D$6943,"*"&$A13&"*",総合一覧!$R$2:$R$6943,L$1) | ... N13: =COUNTIFS(総合一覧!$D$2:$D$6943,"*"&$A13&"*",総合一覧!$R$2:$R$6943,N$1)
... A32: T30 | B32: AI・OCR・翻訳など新技術との連携 | C32: =COUNTIF(総合一覧!$D$2:$D$6943,"*"&A32&"*") | D32: =COUNTIFS(総合一覧!$D$2:$D$6943,"*"&A32&"*",総合一覧!$M$2:$M$6943,">=70") | E32: =COUNTIFS(総合一覧!$D$2:$D$6943,"*"&$A32&"*",総合一覧!$R$2:$R$6943,E$1) | F32: =COUNTIFS(総合一覧!$D$2:$D$6943,"*"&$A32&"*",総合一覧!$R$2:$R$6943,F$1) | G32: =COUNTIFS(総合一覧!$D$2:$D$6943,"*"&$A32&"*",総合一覧!$R$2:$R$6943,G$1) | H32: =COUNTIFS(総合一覧!$D$2:$D$6943,"*"&$A32&"*",総合一覧!$R$2:$R$6943,H$1) | I32: =COUNTIFS(総合一覧!$D$2:$D$6943,"*"&$A32&"*",総合一覧!$R$2:$R$6943,I$1) | J32: =COUNTIFS(総合一覧!$D$2:$D$6943,"*"&$A32&"*",総合一覧!$R$2:$R$6943,J$1) | K32: =COUNTIFS(総合一覧!$D$2:$D$6943,"*"&$A32&"*",総合一覧!$R$2:$R$6943,K$1) | L32: =COUNTIFS(総合一覧!$D$2:$D$6943,"*"&$A32&"*",総合一覧!$R$2:$R$6943,L$1) | ... N32: =COUNTIFS(総合一覧!$D$2:$D$6943,"*"&$A32&"*",総合一覧!$R$2:$R$6943,N$1)
A34: ※「入手方法」「形式」はURLや取得元サイトの傾向から判断した見込みです。実際のダウンロード時に確認します。

Sheet 分野別TOP10
A1: 分野別 上位10件（作成時点の点数で抽出。点数を変えても自動では並び替わりません）
A3: 01
A4: 順 | B4: 名前 | C4: 何をするツールか | D4: 合計 | E4: 地域 | F4: サイト | G4: リンク
A5: 1 | B5: Довольно мощный автонумератор и не только. | C5: 強力な自動連番・値変更 | D5: 54 | E5: ロシア語圏 | F5: dwg.ru | G5: 開く
A6: 2 | B6: INCDEC v 02.17 | C6: 注記の連番・加減算・値交換 | D6: 53 | E6: ロシア語圏 | F6: dwg.ru | G6: 開く
A7: 3 | B7: AsmiTools: TTC.LSP | C7: 文字・表・寸法・属性間で内容コピー | D7: 52 | E7: ロシア語圏 | F7: dwg.ru | G7: 開く
A8: 4 | B8: Довольно мощный копировщик текста и не только | C8: 文字・属性値の強力コピー | D8: 52 | E8: ロシア語圏 | F8: dwg.ru | G8: 開く
A9: 5 | B9: AsmiTools: NUM.LSP | C9: 接頭辞・接尾辞付き動的連番 | D9: 51 | E9: ロシア語圏 | F9: dwg.ru | G9: 開く
A10: 6 | B10: Многозадачный поиск и замена текста по маске | C10: マスク指定で多重検索置換 | D10: 51 | E10: ロシア語圏 | F10: dwg.ru | G10: 開く
A11: 7 | B11: Нумеровщик с префиксом, изменяемой частью и суффиксом | C11: 接頭辞・接尾辞付き連番記入 | D11: 51 | E11: ロシア語圏 | F11: dwg.ru | G11: 開く
A12: 8 | B12: Программа с функциями для действий с текстовыми примитивами. v.1.3 | C12: 文字の連番・四則演算 | D12: 51 | E12: ロシア語圏 | F12: dwg.ru | G12: 開く
A13: 9 | B13: LISP для замены высоты текста на чертеже | C13: 全文字高さを0.5刻みに丸め | D13: 50 | E13: ロシア語圏 | F13: dwg.ru | G13: 開く
A14: 10 | B14: ClearTextsByRadius.LISP | C14: 半径内の重なる文字を間引く | D14: 49 | E14: ロシア語圏 | F14: geodesist.ru | G14: 開く
A16: 文字・テキスト
A17: 順 | B17: 名前 | C17: 何をするツールか | D17: 合計 | E17: 地域 | F17: サイト | G17: リンク
A18: 1 | B18: 文字避让 (@lisp文本) | C18: 重なった単線文字を自動で逃がし配置 | D18: 77 | E18: 中国語圏 | F18: @lisp 应用云 | G18: 開く
A19: 2 | B19: Incremental Numbering Suite | C19: 連番文字・属性を配置 | D19: 76 | E19: 英語圏 | F19: Lee Mac Programming | G19: 開く
A20: 3 | B20: ZW工具 AW 文字自动避让 | C20: 文字を微移動して線・他文字との重なりを回避 | D20: 74 | E20: 中国語圏 | F20: GitHub: y1991427360s/zwcad-autolisp-tools | G20: 開く
A21: 4 | B21: RegExpCnt | C21: 正規表現で文字を置換・連番 | D21: 72 | E21: 英語圏 | F21: CAD Studio | G21: 開く
A22: 5 | B22: TxtOverlap | C22: 重なった文字を検出 | D22: 72 | E22: 英語圏 | F22: CAD Forum | G22: 開く
A23: 6 | B23: Incremental Array | C23: 連番を増やしながら配列複写 | D23: 71 | E23: 英語圏 | F23: Lee Mac Programming | G23: 開く
A24: 7 | B24: Incremental Numbering (NumInc) | C24: 連番テキスト・ブロックを配置 | D24: 70 | E24: 英語圏 | F24: MEP WORK | G24: 開く
A25: 8 | B25: Lisp dịch thuật bản vẽ song ngữ AutoCAD | C25: AIで図面文字を対訳翻訳（有料） | D25: 70 | E25: ベトナム・東南アジア | F25: lisp.vn (AutoLISP Reviewer) | G25: 開く
A26: 9 | B26: 定位压线字 (@lisp文本) | C26: 線と重なっている文字を強調表示 | D26: 70 | E26: 中国語圏 | F26: @lisp 应用云 | G26: 開く
A27: 10 | B27: PDFOCRTEXT PDF转CAD文字OCR | C27: PDF由来の線文字をOCRしてMTEXT化 | D27: 69 | E27: 中国語圏 | F27: GitHub: y1991427360s/pdf2cad-ocr-text-helper | G27: 開く
A29: 02
A30: 順 | B30: 名前 | C30: 何をするツールか | D30: 合計 | E30: 地域 | F30: サイト | G30: リンク
A31: 1 | B31: Визуальный контроль масштабного к-та (DIMLFAC) размеров! | C31: 寸法の尺度係数を色で可視化 | D31: 59 | E31: ロシア語圏 | F31: dwg.ru | G31: 開く
A32: 2 | B32: Программа AutoDim, автоматом строит цепочки размеров, образмеривает окружности и т.д. | C32: 直列寸法や円寸法を自動記入 | D32: 55 | E32: ロシア語圏 | F32: dwg.ru | G32: 開く
A33: 3 | B33: FreeHandDim | C33: 手入力寸法値を検出し赤色化 | D33: 51 | E33: ロシア語圏 | F33: cad.dp.ua | G33: 開く
A34: 4 | B34: AsmiTools: PDIM.LSP | C34: 複数ポリラインに一括寸法 | D34: 48 | E34: ロシア語圏 | F34: dwg.ru | G34: 開く
A35: 5 | B35: Простановка длин полилиний и отрезков в средней точке | C35: 線の中点に長さを記入 | D35: 47 | E35: ロシア語圏 | F35: forum.dwg.ru | G35: 開く
A36: 6 | B36: DimReduct исправление перевернутых размеров | C36: 反転した寸法を正しい向きに修正 | D36: 45 | E36: ロシア語圏 | F36: dwg.ru | G36: 開く
A37: 7 | B37: Нанесение размеров на аксонометрических проекциях | C37: アイソメ図に寸法記入 | D37: 44 | E37: ロシア語圏 | F37: dwg.ru | G37: 開く
A38: 8 | B38: DSK v0.7L - программа для простановки размеров | C38: 公差付き寸法を記入 | D38: 41 | E38: ロシア語圏 | F38: dwg.ru | G38: 開く
A39: 9 | B39: DIMRR | C39: 許容範囲内で実測寸法値を作成 | D39: 40 | E39: ロシア語圏 | F39: ispolnitelnaya-shema.ru | G39: 開く
A40: 10 | B40: Лисп DIMR | C40: 寸法の分母に実測値を記入 | D40: 38 | E40: ロシア語圏 | F40: geodesist.ru | G40: 開く
A42: 寸法
A43: 順 | B43: 名前 | C43: 何をするツールか | D43: 合計 | E43: 地域 | F43: サイト | G43: リンク
A44: 1 | B44: DIMPOLICE | C44: 書き換えられた寸法値を検出（有料） | D44: 73 | E44: 日本 | F44: note (chiko_root) | G44: 開く
A45: 2 | B45: 快速拉线标注—带捕捉 | C45: 線を引くだけで交差箇所に連続寸法 | D45: 72 | E45: 中国語圏 | F45: 明经CAD社区 | G45: 開く
A46: 3 | B46: DIMQuick快速标注_v3.6.9 | C46: スペース囲み選択で連続寸法（天正対応） | D46: 71 | E46: 中国語圏 | F46: 明经CAD社区 | G46: 開く
A47: 4 | B47: OverDimCol (ODC) | C47: 文字上書きされた寸法を強調 | D47: 69 | E47: 英語圏 | F47: CAD Forum | G47: 開く
A48: 5 | B48: Automatic Dimensions | C48: 直線上の要素を自動寸法記入 | D48: 67 | E48: 英語圏 | F48: Cadalyst CAD Tips | G48: 開く
A49: 6 | B49: ScaleKeepDim | C49: 寸法値を保ったまま図形を拡大縮小（有料） | D49: 64 | E49: 日本 | F49: note (chiko_root) | G49: 開く
A50: 7 | B50: EasyDim.lsp | C50: ポリライン全周に寸法記入 | D50: 61 | E50: 英語圏 | F50: CAD Authority | G50: 開く
A51: 8 | B51: QD Dim nhanh siêu tốc trong Cad | C51: 多層寸法を一括自動記入（有料） | D51: 61 | E51: ベトナム・東南アジア | F51: lisp.vn (AutoLISP Reviewer) | G51: 開く
A52: 9 | B52: Automatically Dimension Polylines | C52: ポリラインのY方向寸法を自動記入 | D52: 60 | E52: 英語圏 | F52: Cadalyst CAD Tips | G52: 開く
A53: 10 | B53: DIMSORT | C53: 寸法線を整列し等間隔に配置（有料） | D53: 59 | E53: 日本 | F53: note (chiko_root) | G53: 開く
A55: 03
A56: 順 | B56: 名前 | C56: 何をするツールか | D56: 合計 | E56: 地域 | F56: サイト | G56: リンク
A57: 1 | B57: Редактор расширенных данных для проставки выносок | C57: 拡張データで引出線を記入 | D57: 47 | E57: ロシア語圏 | F57: dwg.ru | G57: 開く
A58: 2 | B58: Текст на мультивыноску лисп | C58: テキストをマルチ引出線に載せ替え | D58: 45 | E58: ロシア語圏 | F58: geodesist.ru | G58: 開く
A59: 3 | B59: Обозначение материала детали. "Ref_Den" от 22.02.06. | C59: 材料表記を便覧から挿入 | D59: 43 | E59: ロシア語圏 | F59: dwg.ru | G59: 開く
A60: 4 | B60: Pos - программа по простановке позиций | C60: 部品番号(ポジション)記入 | D60: 40 | E60: ロシア語圏 | F60: dwg.ru | G60: 開く
A61: 5 | B61: Простановки условных графических обозначений на чертеже по ЕСКД | C61: ESKD記号(粗さ等)を記入 | D61: 39 | E61: ロシア語圏 | F61: dwg.ru | G61: 開く
A62: 6 | B62: Разрезы, виды, сечения (простые, ломаные, двусторонние) | C62: 断面・矢視記号を任意角度で作図 | D62: 39 | E62: ロシア語圏 | F62: dwg.ru | G62: 開く
A63: 7 | B63: OL. Вставка выноски v.1.0 | C63: 構造部材の引出線を挿入 | D63: 37 | E63: ロシア語圏 | F63: dwg.ru | G63: 開く
A64: 8 | B64: rough5 | C64: 表面粗さ記号を挿入 | D64: 35 | E64: ロシア語圏 | F64: cad.dp.ua | G64: 開く
A65: 9 | B65: Udim.lsp | C65: ブロックの拡張データを引出線に表示 | D65: 35 | E65: ロシア語圏 | F65: acad-prog.ru | G65: 開く
A66: 10 | B66: Рисование фигурных скобок с текстом | C66: 文字付き中括弧を作図 | D66: 35 | E66: ロシア語圏 | F66: dwg.ru | G66: 開く
A68: 引出線・注記
A69: 順 | B69: 名前 | C69: 何をするツールか | D69: 合計 | E69: 地域 | F69: サイト | G69: リンク
A70: 1 | B70: Construction Notes Manager | C70: 工事注記バルーンから数量表を自動作成 | D70: 74 | E70: GitHub | F70: GitHub: hawstom/cnm | G70: 開く
A71: 2 | B71: MLeaderSmartAlign | C71: マルチ引出線をライブプレビューで整列 | D71: 69 | E71: GitHub | F71: GitHub: ivashinpavel07/AutoCAD-AutoLISP-MLeaderSmartAlign | G71: 開く
A72: 3 | B72: MLeaderSmartAlignPerimeter | C72: 引出線を外周に沿って配置 | D72: 66 | E72: GitHub | F72: GitHub: ivashinpavel07/AutoCAD-AutoLISP-MLeaderSmartAlign | G72: 開く
A73: 4 | B73: JustifyTextAuto | C73: 文字基点を最寄り引出線側に自動調整（有料） | D73: 60 | E73: 日本 | F73: note (chiko_root) | G73: 開く
A74: 5 | B74: non_overlapping_labels | C74: 重ならないラベルを自動配置 | D74: 60 | E74: GitHub | F74: GitHub: moostang/autolisp | G74: 開く
A75: 6 | B75: Incremental Bubble Labeling | C75: 連番バルーン引出線を配置 | D75: 59 | E75: 英語圏 | F75: Cadalyst CAD Tips | G75: 開く
A76: 7 | B76: DU.lsp | C76: 現DIMSCALEに合わせ注記類を一括更新 | D76: 58 | E76: その他の地域 | F76: Paulo Gil Soto blog | G76: 開く
A77: 8 | B77: Excel 2 Mleader Program | C77: Excelデータをマルチ引出線で配置（有料） | D77: 58 | E77: 英語圏 | F77: Tharwat | G77: 開く
A78: 9 | B78: 动态对齐箭头 引线+文字 | C78: 矢印位置を揃えた引出線注記を動的作図 | D78: 58 | E78: 中国語圏 | F78: 明经CAD社区 | G78: 開く
A79: 10 | B79: QuickCircleNumber 快速带圈编号 | C79: 丸数字を自動増分配置・一括尺度変更・修復 | D79: 57 | E79: 中国語圏 | F79: GitHub: za5132-web/QuickCircleNumber | G79: 開く
A81: 04
A82: 順 | B82: 名前 | C82: 何をするツールか | D82: 合計 | E82: 地域 | F82: サイト | G82: リンク
A83: 1 | B83: blockify - rapair Block. Востанавливает взорваный блок | C83: 分解されたブロックを復元 | D83: 61 | E83: ロシア語圏 | F83: dwg.ru | G83: 開く
A84: 2 | B84: AsmiTools: ATRON.LSP | C84: 挿入後に属性角度0化と位置調整(リアクター) | D84: 53 | E84: ロシア語圏 | F84: dwg.ru | G84: 開く
A85: 3 | B85: Программа заполнения Lookup-a динамических свойств блока из данных таблицы Excel | C85: 動的ブロックのルックアップを表から入力 | D85: 52 | E85: ロシア語圏 | F85: dwg.ru | G85: 開く
A86: 4 | B86: AsmiTools: ATNUM.LSP | C86: 単一属性ブロックで動的連番 | D86: 49 | E86: ロシア語圏 | F86: dwg.ru | G86: 開く
A87: 5 | B87: AsmiTools: VICO.LSP | C87: 動的ブロックの可視状態をコピー | D87: 49 | E87: ロシア語圏 | F87: dwg.ru | G87: 開く
A88: 6 | B88: rename-copypaste | C88: 貼付けで生じたブロック名を整理 | D88: 49 | E88: ロシア語圏 | F88: autolisp.ru | G88: 開く
A89: 7 | B89: Реактор атрибутов блока | C89: 属性編集用リアクター | D89: 49 | E89: ロシア語圏 | F89: dwg.ru | G89: 開く
A90: 8 | B90: Вставка и автоматическая нумерация блоков v.2.2.3 и v.4.1 Test | C90: ブロック挿入と自動連番 | D90: 48 | E90: ロシア語圏 | F90: dwg.ru | G90: 開く
A91: 9 | B91: blockrename | C91: マスク指定でブロック名を一括変更 | D91: 47 | E91: ロシア語圏 | F91: autolisp.ru | G91: 開く
A92: 10 | B92: Программа для переписывания данных из Lookup-a в Excel | C92: ルックアップ表をExcelへ書出し | D92: 47 | E92: ロシア語圏 | F92: dwg.ru | G92: 開く
A94: ブロック・属性
A95: 順 | B95: 名前 | C95: 何をするツールか | D95: 合計 | E95: 地域 | F95: サイト | G95: リンク
A96: 1 | B96: LATT | C96: 属性同士をリアクタで連動（同値・連番・合計）自動更新 | D96: 73 | E96: ヨーロッパ | F96: CADxp (Patrick_35) | G96: 開く
A97: 2 | B97: Sel2BlkRef | C97: 類似図形をブロック参照に置換 | D97: 73 | E97: 英語圏 | F97: CAD Forum | G97: 開く
A98: 3 | B98: Automatic Block Break | C98: ブロック挿入時に線を自動切断 | D98: 72 | E98: 英語圏 | F98: Lee Mac Programming | G98: 開く
A99: 4 | B99: 按路线编号 (@lisp Block) | C99: 曲線ルート順にブロックを連番付け | D99: 72 | E99: 中国語圏 | F99: @lisp 应用云 | G99: 開く
A100: 5 | B100: 分堆建块 (@lisp Block) | C100: 隙間で図形を塊分けし各々ブロック化 | D100: 71 | E100: 中国語圏 | F100: @lisp 应用云 | G100: 開く
A101: 6 | B101: LISP Ánh xạ giá trị đối tượng | C101: 元値変更で参照先を自動更新(リアクタ) | D101: 67 | E101: ベトナム・東南アジア | F101: CADViet | G101: 開く
A102: 7 | B102: 块自动编号 (@lisp Block) | C102: 属性ブロックを上→下・左→右に自動採番 | D102: 66 | E102: 中国語圏 | F102: @lisp 应用云 | G102: 開く
A103: 8 | B103: ATTINC | C103: 属性値を連番で増加 | D103: 64 | E103: 英語圏 | F103: JefferyPSanders.com | G103: 開く
A104: 9 | B104: Automatically Label Attributes | C104: 頂点座標を属性に自動記入 | D104: 64 | E104: 英語圏 | F104: Lee Mac Programming | G104: 開く
A105: 10 | B105: BB | C105: ブロック内図形のプロパティ一括変更 | D105: 64 | E105: 英語圏 | F105: CAD Studio | G105: 開く
A107: 05
A108: 順 | B108: 名前 | C108: 何をするツールか | D108: 合計 | E108: 地域 | F108: サイト | G108: リンク
A109: 1 | B109: Next layer и назад команда хх и zz | C109: 画層を順送り/逆送りで単独表示 | D109: 49 | E109: ロシア語圏 | F109: dwg.ru | G109: 開く
...

Sheet 地域別集計
A1: 地域 | B1: 件数 | C1: 平均点 | D1: 最高点 | E1: 70点以上の件数
A2: 英語圏 | B2: =COUNTIF(総合一覧!$B$2:$B$6943,A2) | C2: =ROUND(AVERAGEIF(総合一覧!$B$2:$B$6943,A2,総合一覧!$M$2:$M$6943),1) | D2: =_xlfn.MAXIFS(総合一覧!$M$2:$M$6943,総合一覧!$B$2:$B$6943,A2) | E2: =COUNTIFS(総合一覧!$B$2:$B$6943,A2,総合一覧!$M$2:$M$6943,">=70")
A3: 日本 | B3: =COUNTIF(総合一覧!$B$2:$B$6943,A3) | C3: =ROUND(AVERAGEIF(総合一覧!$B$2:$B$6943,A3,総合一覧!$M$2:$M$6943),1) | D3: =_xlfn.MAXIFS(総合一覧!$M$2:$M$6943,総合一覧!$B$2:$B$6943,A3) | E3: =COUNTIFS(総合一覧!$B$2:$B$6943,A3,総合一覧!$M$2:$M$6943,">=70")
A4: 中国語圏 | B4: =COUNTIF(総合一覧!$B$2:$B$6943,A4) | C4: =ROUND(AVERAGEIF(総合一覧!$B$2:$B$6943,A4,総合一覧!$M$2:$M$6943),1) | D4: =_xlfn.MAXIFS(総合一覧!$M$2:$M$6943,総合一覧!$B$2:$B$6943,A4) | E4: =COUNTIFS(総合一覧!$B$2:$B$6943,A4,総合一覧!$M$2:$M$6943,">=70")
A5: ロシア語圏 | B5: =COUNTIF(総合一覧!$B$2:$B$6943,A5) | C5: =ROUND(AVERAGEIF(総合一覧!$B$2:$B$6943,A5,総合一覧!$M$2:$M$6943),1) | D5: =_xlfn.MAXIFS(総合一覧!$M$2:$M$6943,総合一覧!$B$2:$B$6943,A5) | E5: =COUNTIFS(総合一覧!$B$2:$B$6943,A5,総合一覧!$M$2:$M$6943,">=70")
A6: ベトナム・東南アジア | B6: =COUNTIF(総合一覧!$B$2:$B$6943,A6) | C6: =ROUND(AVERAGEIF(総合一覧!$B$2:$B$6943,A6,総合一覧!$M$2:$M$6943),1) | D6: =_xlfn.MAXIFS(総合一覧!$M$2:$M$6943,総合一覧!$B$2:$B$6943,A6) | E6: =COUNTIFS(総合一覧!$B$2:$B$6943,A6,総合一覧!$M$2:$M$6943,">=70")
A7: ヨーロッパ | B7: =COUNTIF(総合一覧!$B$2:$B$6943,A7) | C7: =ROUND(AVERAGEIF(総合一覧!$B$2:$B$6943,A7,総合一覧!$M$2:$M$6943),1) | D7: =_xlfn.MAXIFS(総合一覧!$M$2:$M$6943,総合一覧!$B$2:$B$6943,A7) | E7: =COUNTIFS(総合一覧!$B$2:$B$6943,A7,総合一覧!$M$2:$M$6943,">=70")
A8: その他の地域 | B8: =COUNTIF(総合一覧!$B$2:$B$6943,A8) | C8: =ROUND(AVERAGEIF(総合一覧!$B$2:$B$6943,A8,総合一覧!$M$2:$M$6943),1) | D8: =_xlfn.MAXIFS(総合一覧!$M$2:$M$6943,総合一覧!$B$2:$B$6943,A8) | E8: =COUNTIFS(総合一覧!$B$2:$B$6943,A8,総合一覧!$M$2:$M$6943,">=70")
A9: GitHub | B9: =COUNTIF(総合一覧!$B$2:$B$6943,A9) | C9: =ROUND(AVERAGEIF(総合一覧!$B$2:$B$6943,A9,総合一覧!$M$2:$M$6943),1) | D9: =_xlfn.MAXIFS(総合一覧!$M$2:$M$6943,総合一覧!$B$2:$B$6943,A9) | E9: =COUNTIFS(総合一覧!$B$2:$B$6943,A9,総合一覧!$M$2:$M$6943,">=70")
A10: 合計 | B10: =SUM(B2:B9) | C10: =ROUND(AVERAGE(総合一覧!$M$2:$M$6943),1) | D10: =MAX(総合一覧!$M$2:$M$6943) | E10: =SUM(E2:E9)
A12: ※地域ごとに別々のAIが採点したため、地域間で点数の付け方に多少のばらつきがあります（例: 中国語圏はやや高め）。

Sheet 採点基準
A1: 採点基準（各25点満点・合計100点）
A3: 項目 | B3: 内容 | C3: 高得点（22〜25点） | D3: 低得点（0〜7点）
A4: 非代替性 | B4: 今のAutoCAD（2024〜2026、Express Tools含む）の標準機能で代わりがきかないか | C4: 標準機能では実現できない | D4: 標準機能（COUNT、TEXTALIGN、BURST、OVERKILL等）でほぼ同じことができる
A5: 斬新さ | B5: 発想の面白さ・目新しさ | C5: 「その手があったか」という発想（自動更新、動的プレビュー、コマンド連動など） | D5: 単純な設定変更や標準コマンドの言い換え
A6: 時短効果 | B6: 1回あたりの時短 × 使う頻度 | C6: よく使う作業で数分〜数時間を短縮（一括処理・自動集計・自動連番など） | D6: 数回のキー操作分の短縮、関数部品、ゲーム
A7: 汎用性 | B7: どんな図面でも使えるか | C7: ほぼすべての図面で使える（文字・画層・ブロック・一括処理・印刷） | D7: 特定の国の規格・特定製品・特定分野専用
A9: 注記
A10: ・採点はコマンドの説明文をもとにしたAIによる評価で、実際に動かして確認したものではありません。
A11: ・対象: 全地域（英語圏・日本・中国語圏・ロシア語圏・ベトナム/東南アジア・ヨーロッパ・その他・GitHub）。同じ名前・同じコマンドの重複は、点数の高い1件にまとめ「同じツールの別掲載」列に他の掲載先を記載。調査日 2026-09-26〜27。
A12: ・「LISP開発用の部品」はコマンドではなくプログラム内で使う関数のため、時短効果は最大7点としています。
A13: ・点数は「一覧」シートで直接書き換えられます（合計と順位は自動で再計算されます）。
